[
  {
    "section": "ALTO",
    "service_category": "Généralités",
    "qtype": "S",
    "qindex": 1,
    "label": "Comment évaluez-vous votre connaissance générale du RGPD<sup>1</sup> ?<p><small>[1] Le Règlement Général sur la Protection des Données (RGPD) est un texte européen applicable depuis le 25 mai 2018 et qui encadre le traitement de données personnelles sur les territoires de l'Union européenne<p></small>",
    "answers": [
      {
        "aindex": 1,
        "uniqueAnswer": true,
        "atype": "P",
        "label": "0 (Non acquis)",
        "questions_map": [
          {
            "label": "Quel organisme / quelle personne soutient votre PME dans votre mise en conformité au RGPD ?",
            "branch": 0,
            "level": 1,
            "order": 1
          }
        ]
      },
      {
        "aindex": 2,
        "uniqueAnswer": true,
        "atype": "P",
        "label": "1",
        "questions_map": [
          {
            "label": "Quel organisme / quelle personne soutient votre PME dans votre mise en conformité au RGPD ?",
            "branch": 0,
            "level": 1,
            "order": 1
          }
        ]
      },
      {
        "aindex": 3,
        "uniqueAnswer": true,
        "atype": "P",
        "label": "2",
        "questions_map": [
          {
            "label": "Quel organisme / quelle personne soutient votre PME dans votre mise en conformité au RGPD ?",
            "branch": 0,
            "level": 1,
            "order": 1
          }
        ]
      },
      {
        "aindex": 4,
        "uniqueAnswer": true,
        "atype": "P",
        "label": "3",
        "questions_map": [
          {
            "label": "Quel organisme / quelle personne soutient votre PME dans votre mise en conformité au RGPD ?",
            "branch": 0,
            "level": 1,
            "order": 1
          }
        ]
      },
      {
        "aindex": 5,
        "uniqueAnswer": true,
        "atype": "P",
        "label": "4",
        "questions_map": [
          {
            "label": "Quel organisme / quelle personne soutient votre PME dans votre mise en conformité au RGPD ?",
            "branch": 0,
            "level": 1,
            "order": 1
          }
        ]
      },
      {
        "aindex": 6,
        "uniqueAnswer": true,
        "atype": "P",
        "label": "5 (Parfaitment maîtrisé)",
        "questions_map": [
          {
            "label": "Quel organisme / quelle personne soutient votre PME dans votre mise en conformité au RGPD ?",
            "branch": 0,
            "level": 1,
            "order": 1
          }
        ]
      }
    ]
  },
  {
    "section": "ALTO",
    "service_category": "Généralités",
    "qtype": "M",
    "qindex": 2,
    "label": "Quel organisme / quelle personne soutient votre PME dans votre mise en conformité au RGPD ?",
    "answers": [
      {
        "aindex": 1,
        "uniqueAnswer": false,
        "atype": "P",
        "label": "La Commission Nationale pour la Protection des Données (CNPD)",
        "questions_map": [
          {
            "label": "À quel organisme / quelle personne votre entreprise s'adresse-t-elle pour obtenir des informations/une aide en la matière ?",
            "branch": 0,
            "level": 2,
            "order": 1
          }
        ]
      },
      {
        "aindex": 2,
        "uniqueAnswer": false,
        "atype": "P",
        "label": "Un délégué à la protection des données interne",
        "questions_map": [
          {
            "label": "À quel organisme / quelle personne votre entreprise s'adresse-t-elle pour obtenir des informations/une aide en la matière ?",
            "branch": 0,
            "level": 2,
            "order": 1
          }
        ]
      },
      {
        "aindex": 3,
        "uniqueAnswer": false,
        "atype": "P",
        "label": "Un délégué à la protection des données externe",
        "questions_map": [
          {
            "label": "À quel organisme / quelle personne votre entreprise s'adresse-t-elle pour obtenir des informations/une aide en la matière ?",
            "branch": 0,
            "level": 2,
            "order": 1
          }
        ]
      },
      {
        "aindex": 4,
        "uniqueAnswer": false,
        "atype": "P",
        "label": "Un avocat",
        "questions_map": [
          {
            "label": "À quel organisme / quelle personne votre entreprise s'adresse-t-elle pour obtenir des informations/une aide en la matière ?",
            "branch": 0,
            "level": 2,
            "order": 1
          }
        ]
      },
      {
        "aindex": 5,
        "uniqueAnswer": false,
        "atype": "P",
        "label": "Une société de conseil",
        "questions_map": [
          {
            "label": "À quel organisme / quelle personne votre entreprise s'adresse-t-elle pour obtenir des informations/une aide en la matière ?",
            "branch": 0,
            "level": 2,
            "order": 1
          }
        ]
      },
      {
        "aindex": 6,
        "uniqueAnswer": false,
        "atype": "P",
        "label": "Une chambre/union professionnelle",
        "questions_map": [
          {
            "label": "À quel organisme / quelle personne votre entreprise s'adresse-t-elle pour obtenir des informations/une aide en la matière ?",
            "branch": 0,
            "level": 2,
            "order": 1
          }
        ]
      },
      {
        "aindex": 7,
        "uniqueAnswer": false,
        "atype": "P",
        "label": "Notre entreprise n'est pas soutenue par un organisme/une personne extérieure",
        "questions_map": [
          {
            "label": "À quel organisme / quelle personne votre entreprise s'adresse-t-elle pour obtenir des informations/une aide en la matière ?",
            "branch": 0,
            "level": 2,
            "order": 1
          }
        ]
      },
      {
        "aindex": 8,
        "uniqueAnswer": true,
        "atype": "P",
        "label": "Je ne sais pas",
        "questions_map": [
          {
            "label": "À quel organisme / quelle personne votre entreprise s'adresse-t-elle pour obtenir des informations/une aide en la matière ?",
            "branch": 0,
            "level": 2,
            "order": 1
          }
        ]
      }
    ]
  },
  {
    "section": "ALTO",
    "service_category": "Généralités",
    "qtype": "M",
    "qindex": 3,
    "label": "À quel organisme / quelle personne votre entreprise s'adresse-t-elle pour obtenir des informations/une aide en la matière ?",
    "answers": [
      {
        "aindex": 1,
        "uniqueAnswer": false,
        "atype": "P",
        "label": "La Commission Nationale pour la Protection des Données (CNPD)",
        "questions_map": [
          {
            "label": "Veuillez classer les principaux défis auxquels votre entreprise est confrontée, en les déplaçant vers le haut (cliquez et déplacez).",
            "branch": 0,
            "level": 3,
            "order": 1
          }
        ]
      },
      {
        "aindex": 2,
        "uniqueAnswer": false,
        "atype": "P",
        "label": "Un délégué à la protection des données interne",
        "questions_map": [
          {
            "label": "Veuillez classer les principaux défis auxquels votre entreprise est confrontée, en les déplaçant vers le haut (cliquez et déplacez).",
            "branch": 0,
            "level": 3,
            "order": 1
          }
        ]
      },
      {
        "aindex": 3,
        "uniqueAnswer": false,
        "atype": "P",
        "label": "Un délégué à la protection des données externe",
        "questions_map": [
          {
            "label": "Veuillez classer les principaux défis auxquels votre entreprise est confrontée, en les déplaçant vers le haut (cliquez et déplacez).",
            "branch": 0,
            "level": 3,
            "order": 1
          }
        ]
      },
      {
        "aindex": 4,
        "uniqueAnswer": false,
        "atype": "P",
        "label": "Un avocat",
        "questions_map": [
          {
            "label": "Veuillez classer les principaux défis auxquels votre entreprise est confrontée, en les déplaçant vers le haut (cliquez et déplacez).",
            "branch": 0,
            "level": 3,
            "order": 1
          }
        ]
      },
      {
        "aindex": 5,
        "uniqueAnswer": false,
        "atype": "P",
        "label": "Une société de conseil",
        "questions_map": [
          {
            "label": "Veuillez classer les principaux défis auxquels votre entreprise est confrontée, en les déplaçant vers le haut (cliquez et déplacez).",
            "branch": 0,
            "level": 3,
            "order": 1
          }
        ]
      },
      {
        "aindex": 6,
        "uniqueAnswer": false,
        "atype": "P",
        "label": "Une chambre/union professionnelle",
        "questions_map": [
          {
            "label": "Veuillez classer les principaux défis auxquels votre entreprise est confrontée, en les déplaçant vers le haut (cliquez et déplacez).",
            "branch": 0,
            "level": 3,
            "order": 1
          }
        ]
      },
      {
        "aindex": 7,
        "uniqueAnswer": false,
        "atype": "P",
        "label": "Notre entreprise n'est pas soutenue par un organisme/une personne extérieure",
        "questions_map": [
          {
            "label": "Veuillez classer les principaux défis auxquels votre entreprise est confrontée, en les déplaçant vers le haut (cliquez et déplacez).",
            "branch": 0,
            "level": 3,
            "order": 1
          }
        ]
      },
      {
        "aindex": 8,
        "uniqueAnswer": true,
        "atype": "P",
        "label": "Je ne sais pas",
        "questions_map": [
          {
            "label": "Veuillez classer les principaux défis auxquels votre entreprise est confrontée, en les déplaçant vers le haut (cliquez et déplacez).",
            "branch": 0,
            "level": 3,
            "order": 1
          }
        ]
      }
    ]
  },
  {
    "section": "ALTO",
    "service_category": "Défis",
    "qtype": "MS",
    "qindex": 4,
    "label": "Veuillez classer les principaux défis auxquels votre entreprise est confrontée, en les déplaçant vers le haut (cliquez et déplacez).",
    "answers": [
      {
        "aindex": 1,
        "uniqueAnswer": false,
        "atype": "P",
        "label": "J'ai besoin de comprendre si je suis concerné par le RGPD",
        "questions_map": [
          {
            "label": "Êtes-vous responsable de traitement ?",
            "branch": 0,
            "level": 4,
            "order": 1
          }
        ]
      },
      {
        "aindex": 2,
        "uniqueAnswer": false,
        "atype": "P",
        "label": "J'ai besoin de savoir si je suis un responsable de traitement ou un sous-traitant",
        "questions_map": [
          {
            "label": "Êtes-vous responsable de traitement ?",
            "branch": 0,
            "level": 4,
            "order": 1
          }
        ]
      },
      {
        "aindex": 3,
        "uniqueAnswer": false,
        "atype": "P",
        "label": "J'ai besoins d'explications quant à mes obligations RGPD",
        "questions_map": [
          {
            "label": "Êtes-vous responsable de traitement ?",
            "branch": 0,
            "level": 4,
            "order": 1
          }
        ]
      },
      {
        "aindex": 4,
        "uniqueAnswer": false,
        "atype": "P",
        "label": "J'ai besoin de savoir comment documenter la gestion des données",
        "questions_map": [
          {
            "label": "Êtes-vous responsable de traitement ?",
            "branch": 0,
            "level": 4,
            "order": 1
          }
        ]
      },
      {
        "aindex": 5,
        "uniqueAnswer": false,
        "atype": "P",
        "label": "J'ai besoin de savoir ce que doit comporter une politique d'information",
        "questions_map": [
          {
            "label": "Êtes-vous responsable de traitement ?",
            "branch": 0,
            "level": 4,
            "order": 1
          }
        ]
      },
      {
        "aindex": 6,
        "uniqueAnswer": false,
        "atype": "P",
        "label": "J'ai besoin d'explications sur les droits des personnes concernées",
        "questions_map": [
          {
            "label": "Êtes-vous responsable de traitement ?",
            "branch": 0,
            "level": 4,
            "order": 1
          }
        ]
      },
      {
        "aindex": 7,
        "uniqueAnswer": false,
        "atype": "P",
        "label": "J'ai besoin d'explications sur les bases légales adéquates pour chacun de mes traitements de données",
        "questions_map": [
          {
            "label": "Êtes-vous responsable de traitement ?",
            "branch": 0,
            "level": 4,
            "order": 1
          }
        ]
      },
      {
        "aindex": 8,
        "uniqueAnswer": false,
        "atype": "P",
        "label": "J'ai besoin de savoir quand désigner un délégué à la protection des données (DPD ou DPO)",
        "questions_map": [
          {
            "label": "Êtes-vous responsable de traitement ?",
            "branch": 0,
            "level": 4,
            "order": 1
          }
        ]
      },
      {
        "aindex": 9,
        "uniqueAnswer": false,
        "atype": "P",
        "label": "J'ai besoin de savoir combien de temps je dois conserver les données collectées",
        "questions_map": [
          {
            "label": "Êtes-vous responsable de traitement ?",
            "branch": 0,
            "level": 4,
            "order": 1
          }
        ]
      },
      {
        "aindex": 10,
        "uniqueAnswer": false,
        "atype": "P",
        "label": "J'ai besoin de savoir si j'applique le principe de minimisation correctement"
      },
      {
        "questions_map": [
          {
            "label": "Êtes-vous responsable de traitement ?",
            "branch": 0,
            "level": 4,
            "order": 1
          }
        ],
        "aindex": 11,
        "uniqueAnswer": false,
        "atype": "P",
        "label": "J'ai besoin d'informations s'agissant des obligations relatives à la sécurité des données personnelles au regard du RGPD"
      },
      {
        "questions_map": [
          {
            "label": "Êtes-vous responsable de traitement ?",
            "branch": 0,
            "level": 4,
            "order": 1
          }
        ],
        "aindex": 12,
        "uniqueAnswer": false,
        "atype": "P",
        "label": "J'ai besoin d'informations s'agissant des mesures techniques et organisationnelles appropriées aux risques liés à ma gestion des données personnelles"
      },
      {
        "questions_map": [
          {
            "label": "Êtes-vous responsable de traitement ?",
            "branch": 0,
            "level": 4,
            "order": 1
          }
        ],
        "aindex": 13,
        "uniqueAnswer": false,
        "atype": "P",
        "label": "J'ai besoin d'information sur la violation de données"
      },
      {
        "questions_map": [
          {
            "label": "Êtes-vous responsable de traitement ?",
            "branch": 0,
            "level": 4,
            "order": 1
          }
        ],
        "aindex": 14,
        "uniqueAnswer": false,
        "atype": "T",
        "label": "Autre"
      },
      {
        "aindex": 15,
        "uniqueAnswer": true,
        "atype": "P",
        "label": "Je ne sais pas",
        "questions_map": [
          {
            "label": "Êtes-vous responsable de traitement ?",
            "branch": 0,
            "level": 4,
            "order": 1
          }
        ]
      }
    ]
  },
  {
    "section": "ALTO",
    "service_category": "Sous-traitance",
    "qtype": "S",
    "qindex": 5,
    "label": "Êtes-vous responsable de traitement ?",
    "answers": [
      {
        "aindex": 1,
        "uniqueAnswer": true,
        "atype": "P",
        "label": "Oui",
        "questions_map": [
          {
            "label": "Etes-vous un sous-traitant au sens du RGPD ?",
            "branch": 0,
            "level": 5,
            "order": 1
          }
        ]
      },
      {
        "aindex": 2,
        "uniqueAnswer": true,
        "atype": "P",
        "label": "Non",
        "questions_map": [
          {
            "label": "Etes-vous un sous-traitant au sens du RGPD ?",
            "branch": 0,
            "level": 5,
            "order": 1
          }
        ]
      },
      {
        "aindex": 3,
        "uniqueAnswer": true,
        "atype": "P",
        "label": "Je ne sais pas",
        "questions_map": [
          {
            "label": "Etes-vous un sous-traitant au sens du RGPD ?",
            "branch": 0,
            "level": 5,
            "order": 1
          }
        ]
      }
    ]
  },
  {
    "section": "ALTO",
    "service_category": "Sous-traitance",
    "qtype": "S",
    "qindex": 6,
    "label": "Etes-vous un sous-traitant au sens du RGPD ?",
    "answers": [
      {
        "aindex": 1,
        "uniqueAnswer": true,
        "atype": "P",
        "label": "Oui",
        "questions_map": [
          {
            "label": "Connaissez-vous la différence entre la notion de « Responsable du traitement » et la notion de « sous-traitant » ?",
            "branch": 0,
            "level": 6,
            "order": 1
          }
        ]
      },
      {
        "aindex": 2,
        "uniqueAnswer": true,
        "atype": "P",
        "label": "Non",
        "questions_map": [
          {
            "label": "Connaissez-vous la différence entre la notion de « Responsable du traitement » et la notion de « sous-traitant » ?",
            "branch": 0,
            "level": 6,
            "order": 1
          }
        ]
      },
      {
        "aindex": 3,
        "uniqueAnswer": true,
        "atype": "P",
        "label": "Je ne sais pas",
        "questions_map": [
          {
            "label": "Connaissez-vous la différence entre la notion de « Responsable du traitement » et la notion de « sous-traitant » ?",
            "branch": 0,
            "level": 6,
            "order": 1
          }
        ]
      }
    ]
  },
  {
    "section": "ALTO",
    "service_category": "Sous-traitance",
    "qtype": "S",
    "qindex": 7,
    "label": "Connaissez-vous la différence entre la notion de « Responsable du traitement » et la notion de « sous-traitant » ?",
    "answers": [
      {
        "aindex": 1,
        "uniqueAnswer": true,
        "atype": "P",
        "label": "0 (Non acquis)",
        "questions_map": [
          {
            "label": "Connaissez-vous l'étendue de vos responsabilités en qualité de « Responsable du traitement » et/ou de « sous-traitant » ?",
            "branch": 0,
            "level": 7,
            "order": 1
          }
        ]
      },
      {
        "aindex": 2,
        "uniqueAnswer": true,
        "atype": "P",
        "label": "1",
        "questions_map": [
          {
            "label": "Connaissez-vous l'étendue de vos responsabilités en qualité de « Responsable du traitement » et/ou de « sous-traitant » ?",
            "branch": 0,
            "level": 7,
            "order": 1
          }
        ]
      },
      {
        "aindex": 3,
        "uniqueAnswer": true,
        "atype": "P",
        "label": "2",
        "questions_map": [
          {
            "label": "Connaissez-vous l'étendue de vos responsabilités en qualité de « Responsable du traitement » et/ou de « sous-traitant » ?",
            "branch": 0,
            "level": 7,
            "order": 1
          }
        ]
      },
      {
        "aindex": 4,
        "uniqueAnswer": true,
        "atype": "P",
        "label": "3",
        "questions_map": [
          {
            "label": "Connaissez-vous l'étendue de vos responsabilités en qualité de « Responsable du traitement » et/ou de « sous-traitant » ?",
            "branch": 0,
            "level": 7,
            "order": 1
          }
        ]
      },
      {
        "aindex": 5,
        "uniqueAnswer": true,
        "atype": "P",
        "label": "4",
        "questions_map": [
          {
            "label": "Connaissez-vous l'étendue de vos responsabilités en qualité de « Responsable du traitement » et/ou de « sous-traitant » ?",
            "branch": 0,
            "level": 7,
            "order": 1
          }
        ]
      },
      {
        "aindex": 6,
        "uniqueAnswer": true,
        "atype": "P",
        "label": "5 (Parfaitment maîtrisé)",
        "questions_map": [
          {
            "label": "Connaissez-vous l'étendue de vos responsabilités en qualité de « Responsable du traitement » et/ou de « sous-traitant » ?",
            "branch": 0,
            "level": 7,
            "order": 1
          }
        ]
      }
    ]
  },
  {
    "section": "ALTO",
    "service_category": "Sous-traitance",
    "qtype": "S",
    "qindex": 8,
    "label": "Connaissez-vous l'étendue de vos responsabilités en qualité de « Responsable du traitement » et/ou de « sous-traitant » ?",
    "answers": [
      {
        "aindex": 1,
        "uniqueAnswer": true,
        "atype": "P",
        "label": "0 (Non acquis)",
        "questions_map": [
          {
            "label": "Sous-traitez-vous certains de vos traitements<sup>1</sup> de données ? <p><small>[1] Un traitement de données personnelles est une opération, ou ensemble d'opérations, portant sur des données personnelles, quel que soit le procédé utilisé. Le RGPD nomme toute une série de différents types de traitement comme la collecte, l'enregistrement, la modification, la diffusion ou toute autre forme de mise à disposition, ou encore l'effacement et la destruction (p.ex : traitement des salaires, traitement des candidats, listes de clients, listes de client prospects).<p>Note : Les dossiers papiers peuvent également être concernés (s'ils sont structurés, par exemple par un classement alphabétique ou chronologique).<p></small>",
            "branch": 0,
            "level": 8,
            "order": 1
          }
        ]
      },
      {
        "aindex": 2,
        "uniqueAnswer": true,
        "atype": "P",
        "label": "1",
        "questions_map": [
          {
            "label": "Sous-traitez-vous certains de vos traitements<sup>1</sup> de données ? <p><small>[1] Un traitement de données personnelles est une opération, ou ensemble d'opérations, portant sur des données personnelles, quel que soit le procédé utilisé. Le RGPD nomme toute une série de différents types de traitement comme la collecte, l'enregistrement, la modification, la diffusion ou toute autre forme de mise à disposition, ou encore l'effacement et la destruction (p.ex : traitement des salaires, traitement des candidats, listes de clients, listes de client prospects).<p>Note : Les dossiers papiers peuvent également être concernés (s'ils sont structurés, par exemple par un classement alphabétique ou chronologique).<p></small>",
            "branch": 0,
            "level": 8,
            "order": 1
          }
        ]
      },
      {
        "aindex": 3,
        "uniqueAnswer": true,
        "atype": "P",
        "label": "2",
        "questions_map": [
          {
            "label": "Sous-traitez-vous certains de vos traitements<sup>1</sup> de données ? <p><small>[1] Un traitement de données personnelles est une opération, ou ensemble d'opérations, portant sur des données personnelles, quel que soit le procédé utilisé. Le RGPD nomme toute une série de différents types de traitement comme la collecte, l'enregistrement, la modification, la diffusion ou toute autre forme de mise à disposition, ou encore l'effacement et la destruction (p.ex : traitement des salaires, traitement des candidats, listes de clients, listes de client prospects).<p>Note : Les dossiers papiers peuvent également être concernés (s'ils sont structurés, par exemple par un classement alphabétique ou chronologique).<p></small>",
            "branch": 0,
            "level": 8,
            "order": 1
          }
        ]
      },
      {
        "aindex": 4,
        "uniqueAnswer": true,
        "atype": "P",
        "label": "3",
        "questions_map": [
          {
            "label": "Sous-traitez-vous certains de vos traitements<sup>1</sup> de données ? <p><small>[1] Un traitement de données personnelles est une opération, ou ensemble d'opérations, portant sur des données personnelles, quel que soit le procédé utilisé. Le RGPD nomme toute une série de différents types de traitement comme la collecte, l'enregistrement, la modification, la diffusion ou toute autre forme de mise à disposition, ou encore l'effacement et la destruction (p.ex : traitement des salaires, traitement des candidats, listes de clients, listes de client prospects).<p>Note : Les dossiers papiers peuvent également être concernés (s'ils sont structurés, par exemple par un classement alphabétique ou chronologique).<p></small>",
            "branch": 0,
            "level": 8,
            "order": 1
          }
        ]
      },
      {
        "aindex": 5,
        "uniqueAnswer": true,
        "atype": "P",
        "label": "4",
        "questions_map": [
          {
            "label": "Sous-traitez-vous certains de vos traitements<sup>1</sup> de données ? <p><small>[1] Un traitement de données personnelles est une opération, ou ensemble d'opérations, portant sur des données personnelles, quel que soit le procédé utilisé. Le RGPD nomme toute une série de différents types de traitement comme la collecte, l'enregistrement, la modification, la diffusion ou toute autre forme de mise à disposition, ou encore l'effacement et la destruction (p.ex : traitement des salaires, traitement des candidats, listes de clients, listes de client prospects).<p>Note : Les dossiers papiers peuvent également être concernés (s'ils sont structurés, par exemple par un classement alphabétique ou chronologique).<p></small>",
            "branch": 0,
            "level": 8,
            "order": 1
          }
        ]
      },
      {
        "aindex": 6,
        "uniqueAnswer": true,
        "atype": "P",
        "label": "5 (Parfaitment maîtrisé)",
        "questions_map": [
          {
            "label": "Sous-traitez-vous certains de vos traitements<sup>1</sup> de données ? <p><small>[1] Un traitement de données personnelles est une opération, ou ensemble d'opérations, portant sur des données personnelles, quel que soit le procédé utilisé. Le RGPD nomme toute une série de différents types de traitement comme la collecte, l'enregistrement, la modification, la diffusion ou toute autre forme de mise à disposition, ou encore l'effacement et la destruction (p.ex : traitement des salaires, traitement des candidats, listes de clients, listes de client prospects).<p>Note : Les dossiers papiers peuvent également être concernés (s'ils sont structurés, par exemple par un classement alphabétique ou chronologique).<p></small>",
            "branch": 0,
            "level": 8,
            "order": 1
          }
        ]
      }
    ]
  },
  {
    "section": "ALTO",
    "service_category": "Sous-traitance",
    "qtype": "S",
    "qindex": 9,
    "label": "Sous-traitez-vous certains de vos traitements<sup>1</sup> de données ? <p><small>[1] Un traitement de données personnelles est une opération, ou ensemble d'opérations, portant sur des données personnelles, quel que soit le procédé utilisé. Le RGPD nomme toute une série de différents types de traitement comme la collecte, l'enregistrement, la modification, la diffusion ou toute autre forme de mise à disposition, ou encore l'effacement et la destruction (p.ex : traitement des salaires, traitement des candidats, listes de clients, listes de client prospects).<p>Note : Les dossiers papiers peuvent également être concernés (s'ils sont structurés, par exemple par un classement alphabétique ou chronologique).<p></small>",
    "answers": [
      {
        "aindex": 1,
        "uniqueAnswer": true,
        "atype": "P",
        "label": "Oui",
        "questions_map": [
          {
            "label": "Avez-vous conclu un contrat de sous-traitance ?",
            "branch": 0,
            "level": 9,
            "order": 1
          }
        ]
      },
      {
        "aindex": 2,
        "uniqueAnswer": true,
        "atype": "P",
        "label": "Non",
        "questions_map": [
          {
            "label": "Votre entreprise sait-elle comment et quand désigner un délégué à la protection des données (DPD ou DPO) ?",
            "branch": 0,
            "level": 9,
            "order": 1
          }
        ]
      },
      {
        "aindex": 3,
        "uniqueAnswer": true,
        "atype": "P",
        "label": "Je ne sais pas",
        "questions_map": [
          {
            "label": "Votre entreprise sait-elle comment et quand désigner un délégué à la protection des données (DPD ou DPO) ?",
            "branch": 0,
            "level": 9,
            "order": 1
          }
        ]
      }
    ]
  },
  {
    "section": "ALTO",
    "service_category": "Sous-traitance",
    "qtype": "S",
    "qindex": 10,
    "label": "Avez-vous conclu un contrat de sous-traitance ?",
    "answers": [
      {
        "aindex": 1,
        "uniqueAnswer": true,
        "atype": "P",
        "label": "Oui",
        "questions_map": [
          {
            "label": "Votre entreprise sait-elle comment et quand désigner un délégué à la protection des données (DPD ou DPO) ?",
            "branch": 0,
            "level": 10,
            "order": 1
          }
        ]
      },
      {
        "aindex": 2,
        "uniqueAnswer": true,
        "atype": "P",
        "label": "Non",
        "questions_map": [
          {
            "label": "Votre entreprise sait-elle comment et quand désigner un délégué à la protection des données (DPD ou DPO) ?",
            "branch": 0,
            "level": 10,
            "order": 1
          }
        ]
      },
      {
        "aindex": 3,
        "uniqueAnswer": true,
        "atype": "P",
        "label": "En cours de projet",
        "questions_map": [
          {
            "label": "Votre entreprise sait-elle comment et quand désigner un délégué à la protection des données (DPD ou DPO) ?",
            "branch": 0,
            "level": 10,
            "order": 1
          }
        ]
      }
    ]
  },
  {
    "section": "ALTO",
    "service_category": "Principes",
    "qtype": "S",
    "qindex": 11,
    "label": "Votre entreprise sait-elle comment et quand désigner un délégué à la protection des données (DPD ou DPO) ?",
    "answers": [
      {
        "aindex": 1,
        "uniqueAnswer": true,
        "atype": "P",
        "label": "Oui",
        "questions_map": [
          {
            "label": "Votre entreprise dispose-t-elle d'une liste des traitements de données ?",
            "branch": 0,
            "level": 11,
            "order": 1
          }
        ]
      },
      {
        "aindex": 2,
        "uniqueAnswer": true,
        "atype": "P",
        "label": "Non",
        "questions_map": [
          {
            "label": "Votre entreprise dispose-t-elle d'une liste des traitements de données ?",
            "branch": 0,
            "level": 11,
            "order": 1
          }
        ]
      }
    ]
  },
  {
    "section": "ALTO",
    "service_category": "Principes",
    "qtype": "S",
    "qindex": 12,
    "label": "Votre entreprise dispose-t-elle d'une liste des traitements de données ?",
    "answers": [
      {
        "aindex": 1,
        "uniqueAnswer": true,
        "atype": "P",
        "label": "Oui",
        "questions_map": [
          {
            "label": "Votre entreprise a-t-elle établi des finalités claires pour ses traitements de données ?",
            "branch": 0,
            "level": 12,
            "order": 1
          }
        ]
      },
      {
        "aindex": 2,
        "uniqueAnswer": true,
        "atype": "P",
        "label": "Non",
        "questions_map": [
          {
            "label": "Votre entreprise a-t-elle établi des finalités claires pour ses traitements de données ?",
            "branch": 0,
            "level": 12,
            "order": 1
          }
        ]
      },
      {
        "aindex": 3,
        "uniqueAnswer": true,
        "atype": "P",
        "label": "En cours de projet",
        "questions_map": [
          {
            "label": "Votre entreprise a-t-elle établi des finalités claires pour ses traitements de données ?",
            "branch": 0,
            "level": 12,
            "order": 1
          }
        ]
      },
      {
        "aindex": 4,
        "uniqueAnswer": true,
        "atype": "P",
        "label": "Je ne sais pas",
        "questions_map": [
          {
            "label": "Votre entreprise a-t-elle établi des finalités claires pour ses traitements de données ?",
            "branch": 0,
            "level": 12,
            "order": 1
          }
        ]
      }
    ]
  },
  {
    "section": "ALTO",
    "service_category": "Principes",
    "qtype": "S",
    "qindex": 13,
    "label": "Votre entreprise a-t-elle établi des finalités claires pour ses traitements de données ?",
    "answers": [
      {
        "aindex": 1,
        "uniqueAnswer": true,
        "atype": "P",
        "label": "Oui",
        "questions_map": [
          {
            "label": "Votre entreprise a-t-elle identifié des bases légales spécifiques pour ses traitements de données ?",
            "branch": 0,
            "level": 13,
            "order": 1
          }
        ]
      },
      {
        "aindex": 2,
        "uniqueAnswer": true,
        "atype": "P",
        "label": "Non",
        "questions_map": [
          {
            "label": "Votre entreprise a-t-elle identifié des bases légales spécifiques pour ses traitements de données ?",
            "branch": 0,
            "level": 13,
            "order": 1
          }
        ]
      },
      {
        "aindex": 3,
        "uniqueAnswer": true,
        "atype": "P",
        "label": "En cours de projet",
        "questions_map": [
          {
            "label": "Votre entreprise a-t-elle identifié des bases légales spécifiques pour ses traitements de données ?",
            "branch": 0,
            "level": 13,
            "order": 1
          }
        ]
      },
      {
        "aindex": 4,
        "uniqueAnswer": true,
        "atype": "P",
        "label": "Je ne sais pas",
        "questions_map": [
          {
            "label": "Votre entreprise a-t-elle identifié des bases légales spécifiques pour ses traitements de données ?",
            "branch": 0,
            "level": 13,
            "order": 1
          }
        ]
      }
    ]
  },
  {
    "section": "ALTO",
    "service_category": "Principes",
    "qtype": "S",
    "qindex": 14,
    "label": "Votre entreprise a-t-elle identifié des bases légales spécifiques pour ses traitements de données ?",
    "answers": [
      {
        "aindex": 1,
        "uniqueAnswer": true,
        "atype": "P",
        "label": "Oui",
        "questions_map": [
          {
            "label": "Votre entreprise a-t-elle mis en œuvre le principe de minimisation des données consistant à n'utiliser que les données nécessaires à la réalisation de ses traitements ?",
            "branch": 0,
            "level": 14,
            "order": 1
          }
        ]
      },
      {
        "aindex": 2,
        "uniqueAnswer": true,
        "atype": "P",
        "label": "Non",
        "questions_map": [
          {
            "label": "Votre entreprise a-t-elle mis en œuvre le principe de minimisation des données consistant à n'utiliser que les données nécessaires à la réalisation de ses traitements ?",
            "branch": 0,
            "level": 14,
            "order": 1
          }
        ]
      },
      {
        "aindex": 3,
        "uniqueAnswer": true,
        "atype": "P",
        "label": "En cours de projet",
        "questions_map": [
          {
            "label": "Votre entreprise a-t-elle mis en œuvre le principe de minimisation des données consistant à n'utiliser que les données nécessaires à la réalisation de ses traitements ?",
            "branch": 0,
            "level": 14,
            "order": 1
          }
        ]
      },
      {
        "aindex": 4,
        "uniqueAnswer": true,
        "atype": "P",
        "label": "Je ne sais pas",
        "questions_map": [
          {
            "label": "Votre entreprise a-t-elle mis en œuvre le principe de minimisation des données consistant à n'utiliser que les données nécessaires à la réalisation de ses traitements ?",
            "branch": 0,
            "level": 14,
            "order": 1
          }
        ]
      }
    ]
  },
  {
    "section": "ALTO",
    "service_category": "Principes",
    "qtype": "S",
    "qindex": 15,
    "label": "Votre entreprise a-t-elle mis en œuvre le principe de minimisation des données consistant à n'utiliser que les données nécessaires à la réalisation de ses traitements ?",
    "answers": [
      {
        "aindex": 1,
        "uniqueAnswer": true,
        "atype": "P",
        "label": "Oui",
        "questions_map": [
          {
            "label": "Votre entreprise a-t-elle connaissance des principes « Privacy by default / Privacy by design »<sup>1</sup> ?<p><small>[1] Le respect de la vie privée par défaut / le respect de la vie privée dès la conception<p></small>",
            "branch": 0,
            "level": 15,
            "order": 1
          }
        ]
      },
      {
        "aindex": 2,
        "uniqueAnswer": true,
        "atype": "P",
        "label": "Non",
        "questions_map": [
          {
            "label": "Votre entreprise a-t-elle connaissance des principes « Privacy by default / Privacy by design »<sup>1</sup> ?<p><small>[1] Le respect de la vie privée par défaut / le respect de la vie privée dès la conception<p></small>",
            "branch": 0,
            "level": 15,
            "order": 1
          }
        ]
      },
      {
        "aindex": 3,
        "uniqueAnswer": true,
        "atype": "P",
        "label": "En cours de projet",
        "questions_map": [
          {
            "label": "Votre entreprise a-t-elle connaissance des principes « Privacy by default / Privacy by design »<sup>1</sup> ?<p><small>[1] Le respect de la vie privée par défaut / le respect de la vie privée dès la conception<p></small>",
            "branch": 0,
            "level": 15,
            "order": 1
          }
        ]
      },
      {
        "aindex": 4,
        "uniqueAnswer": true,
        "atype": "P",
        "label": "Je ne sais pas",
        "questions_map": [
          {
            "label": "Votre entreprise a-t-elle connaissance des principes « Privacy by default / Privacy by design »<sup>1</sup> ?<p><small>[1] Le respect de la vie privée par défaut / le respect de la vie privée dès la conception<p></small>",
            "branch": 0,
            "level": 15,
            "order": 1
          }
        ]
      }
    ]
  },
  {
    "section": "ALTO",
    "service_category": "Principes",
    "qtype": "S",
    "qindex": 16,
    "label": "Votre entreprise a-t-elle connaissance des principes « Privacy by default / Privacy by design »<sup>1</sup> ?<p><small>[1] Le respect de la vie privée par défaut / le respect de la vie privée dès la conception<p></small>",
    "answers": [
      {
        "aindex": 1,
        "uniqueAnswer": true,
        "atype": "P",
        "label": "Oui",
        "questions_map": [
          {
            "label": "Votre entreprise informe-t-elle les personnes concernées (ex : salariés, clients, etc.) des traitements effectués sur leurs données personnelles ?",
            "branch": 0,
            "level": 16,
            "order": 1
          }
        ]
      },
      {
        "aindex": 2,
        "uniqueAnswer": true,
        "atype": "P",
        "label": "Non",
        "questions_map": [
          {
            "label": "Votre entreprise informe-t-elle les personnes concernées (ex : salariés, clients, etc.) des traitements effectués sur leurs données personnelles ?",
            "branch": 0,
            "level": 16,
            "order": 1
          }
        ]
      },
      {
        "aindex": 3,
        "uniqueAnswer": true,
        "atype": "P",
        "label": "Je ne sais pas",
        "questions_map": [
          {
            "label": "Votre entreprise informe-t-elle les personnes concernées (ex : salariés, clients, etc.) des traitements effectués sur leurs données personnelles ?",
            "branch": 0,
            "level": 16,
            "order": 1
          }
        ]
      }
    ]
  },
  {
    "section": "ALTO",
    "service_category": "Principes",
    "qtype": "S",
    "qindex": 17,
    "label": "Votre entreprise informe-t-elle les personnes concernées (ex : salariés, clients, etc.) des traitements effectués sur leurs données personnelles ?",
    "answers": [
      {
        "aindex": 1,
        "uniqueAnswer": true,
        "atype": "P",
        "label": "Oui",
        "questions_map": [
          {
            "label": "Votre entreprise informe-t-elle les personnes concernées (ex. : salariés, clients, etc.) sur leurs droits prévus par le RGPD ?",
            "branch": 0,
            "level": 17,
            "order": 1
          }
        ]
      },
      {
        "aindex": 2,
        "uniqueAnswer": true,
        "atype": "P",
        "label": "Non",
        "questions_map": [
          {
            "label": "Votre entreprise informe-t-elle les personnes concernées (ex. : salariés, clients, etc.) sur leurs droits prévus par le RGPD ?",
            "branch": 0,
            "level": 17,
            "order": 1
          }
        ]
      },
      {
        "aindex": 3,
        "uniqueAnswer": true,
        "atype": "P",
        "label": "En cours de projet",
        "questions_map": [
          {
            "label": "Votre entreprise informe-t-elle les personnes concernées (ex. : salariés, clients, etc.) sur leurs droits prévus par le RGPD ?",
            "branch": 0,
            "level": 17,
            "order": 1
          }
        ]
      },
      {
        "aindex": 4,
        "uniqueAnswer": true,
        "atype": "P",
        "label": "Je ne sais pas",
        "questions_map": [
          {
            "label": "Votre entreprise informe-t-elle les personnes concernées (ex. : salariés, clients, etc.) sur leurs droits prévus par le RGPD ?",
            "branch": 0,
            "level": 17,
            "order": 1
          }
        ]
      }
    ]
  },
  {
    "section": "ALTO",
    "service_category": "Principes",
    "qtype": "S",
    "qindex": 18,
    "label": "Votre entreprise informe-t-elle les personnes concernées (ex. : salariés, clients, etc.) sur leurs droits prévus par le RGPD ?",
    "answers": [
      {
        "aindex": 1,
        "uniqueAnswer": true,
        "atype": "P",
        "label": "Oui",
        "questions_map": [
          {
            "label": "Votre entreprise applique-t-elle des délais de conservation adaptés à la nature des données traitées ?",
            "branch": 0,
            "level": 18,
            "order": 1
          }
        ]
      },
      {
        "aindex": 2,
        "uniqueAnswer": true,
        "atype": "P",
        "label": "Non",
        "questions_map": [
          {
            "label": "Votre entreprise applique-t-elle des délais de conservation adaptés à la nature des données traitées ?",
            "branch": 0,
            "level": 18,
            "order": 1
          }
        ]
      },
      {
        "aindex": 3,
        "uniqueAnswer": true,
        "atype": "P",
        "label": "En cours de projet",
        "questions_map": [
          {
            "label": "Votre entreprise applique-t-elle des délais de conservation adaptés à la nature des données traitées ?",
            "branch": 0,
            "level": 18,
            "order": 1
          }
        ]
      },
      {
        "aindex": 4,
        "uniqueAnswer": true,
        "atype": "P",
        "label": "Je ne sais pas",
        "questions_map": [
          {
            "label": "Votre entreprise applique-t-elle des délais de conservation adaptés à la nature des données traitées ?",
            "branch": 0,
            "level": 18,
            "order": 1
          }
        ]
      }
    ]
  },
  {
    "section": "ALTO",
    "service_category": "Principes",
    "qtype": "S",
    "qindex": 19,
    "label": "Votre entreprise applique-t-elle des délais de conservation adaptés à la nature des données traitées ?",
    "answers": [
      {
        "aindex": 1,
        "uniqueAnswer": true,
        "atype": "P",
        "label": "Oui",
        "questions_map": [
          {
            "label": "Votre entreprise héberge-t-elle les données traitées dans un lieu<sup>1</sup> de stockage dont la sécurité est adaptée à la sensibilité des données ?<p><small>[1] Il peut s'agir du local physique (ex. : salle serveurs, armoire papier, etc.) ou du lieu de stockage effectif (bases de données, archives, back-ups, classeurs physiques, etc.)<p></small></p>",
            "branch": 0,
            "level": 19,
            "order": 1
          }
        ]
      },
      {
        "aindex": 2,
        "uniqueAnswer": true,
        "atype": "P",
        "label": "Non",
        "questions_map": [
          {
            "label": "Votre entreprise héberge-t-elle les données traitées dans un lieu<sup>1</sup> de stockage dont la sécurité est adaptée à la sensibilité des données ?<p><small>[1] Il peut s'agir du local physique (ex. : salle serveurs, armoire papier, etc.) ou du lieu de stockage effectif (bases de données, archives, back-ups, classeurs physiques, etc.)<p></small></p>",
            "branch": 0,
            "level": 19,
            "order": 1
          }
        ]
      },
      {
        "aindex": 3,
        "uniqueAnswer": true,
        "atype": "P",
        "label": "En cours de projet",
        "questions_map": [
          {
            "label": "Votre entreprise héberge-t-elle les données traitées dans un lieu<sup>1</sup> de stockage dont la sécurité est adaptée à la sensibilité des données ?<p><small>[1] Il peut s'agir du local physique (ex. : salle serveurs, armoire papier, etc.) ou du lieu de stockage effectif (bases de données, archives, back-ups, classeurs physiques, etc.)<p></small></p>",
            "branch": 0,
            "level": 19,
            "order": 1
          }
        ]
      },
      {
        "aindex": 4,
        "uniqueAnswer": true,
        "atype": "P",
        "label": "Je ne sais pas",
        "questions_map": [
          {
            "label": "Votre entreprise héberge-t-elle les données traitées dans un lieu<sup>1</sup> de stockage dont la sécurité est adaptée à la sensibilité des données ?<p><small>[1] Il peut s'agir du local physique (ex. : salle serveurs, armoire papier, etc.) ou du lieu de stockage effectif (bases de données, archives, back-ups, classeurs physiques, etc.)<p></small></p>",
            "branch": 0,
            "level": 19,
            "order": 1
          }
        ]
      }
    ]
  },
  {
    "section": "ALTO",
    "service_category": "Principes",
    "qtype": "S",
    "qindex": 20,
    "label": "Votre entreprise héberge-t-elle les données traitées dans un lieu<sup>1</sup> de stockage dont la sécurité est adaptée à la sensibilité des données ?<p><small>[1] Il peut s'agir du local physique (ex. : salle serveurs, armoire papier, etc.) ou du lieu de stockage effectif (bases de données, archives, back-ups, classeurs physiques, etc.)<p></small></p>",
    "answers": [
      {
        "aindex": 1,
        "uniqueAnswer": true,
        "atype": "P",
        "label": "Oui",
        "questions_map": [
          {
            "label": "Quelle documentation votre entreprise a mis en place afin de démontrer que sa gestion des données est conforme au RGPD ?",
            "branch": 0,
            "level": 20,
            "order": 1
          }
        ]
      },
      {
        "aindex": 2,
        "uniqueAnswer": true,
        "atype": "P",
        "label": "Non",
        "questions_map": [
          {
            "label": "Quelle documentation votre entreprise a mis en place afin de démontrer que sa gestion des données est conforme au RGPD ?",
            "branch": 0,
            "level": 20,
            "order": 1
          }
        ]
      },
      {
        "aindex": 3,
        "uniqueAnswer": true,
        "atype": "P",
        "label": "En cours de projet",
        "questions_map": [
          {
            "label": "Quelle documentation votre entreprise a mis en place afin de démontrer que sa gestion des données est conforme au RGPD ?",
            "branch": 0,
            "level": 20,
            "order": 1
          }
        ]
      },
      {
        "aindex": 4,
        "uniqueAnswer": true,
        "atype": "P",
        "label": "Je ne sais pas",
        "questions_map": [
          {
            "label": "Quelle documentation votre entreprise a mis en place afin de démontrer que sa gestion des données est conforme au RGPD ?",
            "branch": 0,
            "level": 20,
            "order": 1
          }
        ]
      }
    ]
  },
  {
    "section": "ALTO",
    "service_category": "Principes",
    "qtype": "M",
    "qindex": 21,
    "label": "Quelle documentation votre entreprise a mis en place afin de démontrer que sa gestion des données est conforme au RGPD ?",
    "answers": [
      {
        "aindex": 1,
        "uniqueAnswer": false,
        "atype": "P",
        "label": "Politiques de protection des données",
        "questions_map": [
          {
            "label": "Avez-vous conscience des risques liés à la gestion des données ?",
            "branch": 0,
            "level": 21,
            "order": 1
          }
        ]
      },
      {
        "aindex": 2,
        "uniqueAnswer": false,
        "atype": "P",
        "label": "Contrat de sous-traitance",
        "questions_map": [
          {
            "label": "Avez-vous conscience des risques liés à la gestion des données ?",
            "branch": 0,
            "level": 21,
            "order": 1
          }
        ]
      },
      {
        "aindex": 3,
        "uniqueAnswer": false,
        "atype": "P",
        "label": "Annexe au contrat de travail (information relative à la gestion des données des salariés)",
        "questions_map": [
          {
            "label": "Avez-vous conscience des risques liés à la gestion des données ?",
            "branch": 0,
            "level": 21,
            "order": 1
          }
        ]
      },
      {
        "aindex": 4,
        "uniqueAnswer": false,
        "atype": "P",
        "label": "Registres des activités de traitements",
        "questions_map": [
          {
            "label": "Avez-vous conscience des risques liés à la gestion des données ?",
            "branch": 0,
            "level": 21,
            "order": 1
          }
        ]
      },
      {
        "aindex": 5,
        "uniqueAnswer": false,
        "atype": "P",
        "label": "Procédure interne de gestion des violations de données",
        "questions_map": [
          {
            "label": "Avez-vous conscience des risques liés à la gestion des données ?",
            "branch": 0,
            "level": 21,
            "order": 1
          }
        ]
      },
      {
        "aindex": 6,
        "uniqueAnswer": false,
        "atype": "P",
        "label": "Procédure interne sur l'exercice des droits des personnes concernées",
        "questions_map": [
          {
            "label": "Avez-vous conscience des risques liés à la gestion des données ?",
            "branch": 0,
            "level": 21,
            "order": 1
          }
        ]
      },
      {
        "aindex": 7,
        "uniqueAnswer": false,
        "atype": "P",
        "label": "Analyses d'impact",
        "questions_map": [
          {
            "label": "Avez-vous conscience des risques liés à la gestion des données ?",
            "branch": 0,
            "level": 21,
            "order": 1
          }
        ]
      },
      {
        "aindex": 8,
        "uniqueAnswer": false,
        "atype": "P",
        "label": "Clauses contractuelles types (transfert pays-tiers)",
        "questions_map": [
          {
            "label": "Avez-vous conscience des risques liés à la gestion des données ?",
            "branch": 0,
            "level": 21,
            "order": 1
          }
        ]
      },
      {
        "aindex": 9,
        "uniqueAnswer": false,
        "atype": "P",
        "label": "Document de recueil du consentement",
        "questions_map": [
          {
            "label": "Avez-vous conscience des risques liés à la gestion des données ?",
            "branch": 0,
            "level": 21,
            "order": 1
          }
        ]
      },
      {
        "aindex": 10,
        "uniqueAnswer": true,
        "atype": "P",
        "label": "Je ne sais pas",
        "questions_map": [
          {
            "label": "Avez-vous conscience des risques liés à la gestion des données ?",
            "branch": 0,
            "level": 21,
            "order": 1
          }
        ]
      }
    ]
  },
  {
    "section": "ALTO",
    "service_category": "Risques",
    "qtype": "S",
    "qindex": 22,
    "label": "Avez-vous conscience des risques liés à la gestion des données ?",
    "answers": [
      {
        "aindex": 1,
        "uniqueAnswer": false,
        "atype": "P",
        "label": "0 (Non acquis)",
        "questions_map": [
          {
            "label": "Quels risques ont été identifiés par votre entreprise ?",
            "branch": 0,
            "level": 22,
            "order": 1
          }
        ]
      },
      {
        "aindex": 2,
        "uniqueAnswer": true,
        "atype": "P",
        "label": "1",
        "questions_map": [
          {
            "label": "Quels risques ont été identifiés par votre entreprise ?",
            "branch": 0,
            "level": 22,
            "order": 1
          }
        ]
      },
      {
        "aindex": 3,
        "uniqueAnswer": true,
        "atype": "P",
        "label": "2",
        "questions_map": [
          {
            "label": "Quels risques ont été identifiés par votre entreprise ?",
            "branch": 0,
            "level": 22,
            "order": 1
          }
        ]
      },
      {
        "aindex": 4,
        "uniqueAnswer": true,
        "atype": "P",
        "label": "3",
        "questions_map": [
          {
            "label": "Quels risques ont été identifiés par votre entreprise ?",
            "branch": 0,
            "level": 22,
            "order": 1
          }
        ]
      },
      {
        "aindex": 5,
        "uniqueAnswer": true,
        "atype": "P",
        "label": "4",
        "questions_map": [
          {
            "label": "Quels risques ont été identifiés par votre entreprise ?",
            "branch": 0,
            "level": 22,
            "order": 1
          }
        ]
      },
      {
        "aindex": 6,
        "uniqueAnswer": true,
        "atype": "P",
        "label": "5 (Parfaitment maîtrisé)",
        "questions_map": [
          {
            "label": "Quels risques ont été identifiés par votre entreprise ?",
            "branch": 0,
            "level": 22,
            "order": 1
          }
        ]
      }
    ]
  },
  {
    "section": "ALTO",
    "service_category": "Risques",
    "qtype": "M",
    "qindex": 23,
    "label": "Quels risques ont été identifiés par votre entreprise ?",
    "answers": [
      {
        "aindex": 1,
        "uniqueAnswer": false,
        "atype": "P",
        "label": "Risques internes (humain, ex : perte de clé USB)",
        "questions_map": [
          {
            "label": "Votre entreprise a-t-elle une vue d'ensemble sur les flux des données ?",
            "branch": 0,
            "level": 23,
            "order": 1
          }
        ]
      },
      {
        "aindex": 2,
        "uniqueAnswer": false,
        "atype": "P",
        "label": "Risques externes (cyber-attaques)",
        "questions_map": [
          {
            "label": "Votre entreprise a-t-elle une vue d'ensemble sur les flux des données ?",
            "branch": 0,
            "level": 23,
            "order": 1
          }
        ]
      },
      {
        "aindex": 3,
        "uniqueAnswer": false,
        "atype": "P",
        "label": "Risques liés à l'usage de technologies",
        "questions_map": [
          {
            "label": "Votre entreprise a-t-elle une vue d'ensemble sur les flux des données ?",
            "branch": 0,
            "level": 23,
            "order": 1
          }
        ]
      },
      {
        "aindex": 4,
        "uniqueAnswer": false,
        "atype": "P",
        "label": "Accidents (ex. : pannes informatiques, incendies, inondations, etc.)",
        "questions_map": [
          {
            "label": "Votre entreprise a-t-elle une vue d'ensemble sur les flux des données ?",
            "branch": 0,
            "level": 23,
            "order": 1
          }
        ]
      },
      {
        "aindex": 5,
        "uniqueAnswer": false,
        "atype": "P",
        "label": "Risques liés aux traitements de données, tels que la prise de décision automatique et la surveillance",
        "questions_map": [
          {
            "label": "Votre entreprise a-t-elle une vue d'ensemble sur les flux des données ?",
            "branch": 0,
            "level": 23,
            "order": 1
          }
        ]
      },
      {
        "aindex": 6,
        "uniqueAnswer": false,
        "atype": "P",
        "label": "Risques liés aux données traitées dites sensibles (ex : origine raciale, opinion politique et religieuse, orientation sexuelle, biométrie, etc.)",
        "questions_map": [
          {
            "label": "Votre entreprise a-t-elle une vue d'ensemble sur les flux des données ?",
            "branch": 0,
            "level": 23,
            "order": 1
          }
        ]
      },
      {
        "aindex": 7,
        "uniqueAnswer": false,
        "atype": "P",
        "label": "Risques liés aux transferts dans des pays situés en dehors de l'Union européenne",
        "questions_map": [
          {
            "label": "Votre entreprise a-t-elle une vue d'ensemble sur les flux des données ?",
            "branch": 0,
            "level": 23,
            "order": 1
          }
        ]
      },
      {
        "aindex": 8,
        "uniqueAnswer": false,
        "atype": "P",
        "label": "Risques liés aux traitements de données de personnes vulnérables (ex : mineur)",
        "questions_map": [
          {
            "label": "Votre entreprise a-t-elle une vue d'ensemble sur les flux des données ?",
            "branch": 0,
            "level": 23,
            "order": 1
          }
        ]
      },
      {
        "aindex": 9,
        "uniqueAnswer": true,
        "atype": "P",
        "label": "Je ne sais pas",
        "questions_map": [
          {
            "label": "Votre entreprise a-t-elle une vue d'ensemble sur les flux des données ?",
            "branch": 0,
            "level": 23,
            "order": 1
          }
        ]
      }
    ]
  },
  {
    "section": "ALTO",
    "service_category": "Risques",
    "qtype": "S",
    "qindex": 24,
    "label": "Votre entreprise a-t-elle une vue d'ensemble sur les flux des données ?",
    "answers": [
      {
        "aindex": 1,
        "uniqueAnswer": true,
        "atype": "P",
        "label": "Oui",
        "questions_map": [
          {
            "label": "Votre entreprise a-t-elle mis en place des mesures pour garantir la sécurité des données ?",
            "branch": 0,
            "level": 24,
            "order": 1
          }
        ]
      },
      {
        "aindex": 2,
        "uniqueAnswer": true,
        "atype": "P",
        "label": "Non",
        "questions_map": [
          {
            "label": "Votre entreprise a-t-elle mis en place des mesures pour garantir la sécurité des données ?",
            "branch": 0,
            "level": 24,
            "order": 1
          }
        ]
      },
      {
        "aindex": 3,
        "uniqueAnswer": true,
        "atype": "P",
        "label": "En cours de projet",
        "questions_map": [
          {
            "label": "Votre entreprise a-t-elle mis en place des mesures pour garantir la sécurité des données ?",
            "branch": 0,
            "level": 24,
            "order": 1
          }
        ]
      },
      {
        "aindex": 4,
        "uniqueAnswer": true,
        "atype": "P",
        "label": "Je ne sais pas",
        "questions_map": [
          {
            "label": "Votre entreprise a-t-elle mis en place des mesures pour garantir la sécurité des données ?",
            "branch": 0,
            "level": 24,
            "order": 1
          }
        ]
      }
    ]
  },
  {
    "section": "ALTO",
    "service_category": "Risques",
    "qtype": "S",
    "qindex": 25,
    "label": "Votre entreprise a-t-elle mis en place des mesures pour garantir la sécurité des données ?",
    "answers": [
      {
        "aindex": 1,
        "uniqueAnswer": true,
        "atype": "P",
        "label": "Oui",
        "questions_map": [
          {
            "label": "Votre entreprise sait-elle comment réagir en cas  de fuites ou de destructions de données personnelles (data breach) ?",
            "branch": 0,
            "level": 25,
            "order": 1
          }
        ]
      },
      {
        "aindex": 2,
        "uniqueAnswer": true,
        "atype": "P",
        "label": "Non",
        "questions_map": [
          {
            "label": "Votre entreprise sait-elle comment réagir en cas  de fuites ou de destructions de données personnelles (data breach) ?",
            "branch": 0,
            "level": 25,
            "order": 1
          }
        ]
      },
      {
        "aindex": 3,
        "uniqueAnswer": true,
        "atype": "P",
        "label": "En cours de projet",
        "questions_map": [
          {
            "label": "Votre entreprise sait-elle comment réagir en cas  de fuites ou de destructions de données personnelles (data breach) ?",
            "branch": 0,
            "level": 25,
            "order": 1
          }
        ]
      },
      {
        "aindex": 4,
        "uniqueAnswer": true,
        "atype": "P",
        "label": "Je ne sais pas",
        "questions_map": [
          {
            "label": "Votre entreprise sait-elle comment réagir en cas  de fuites ou de destructions de données personnelles (data breach) ?",
            "branch": 0,
            "level": 25,
            "order": 1
          }
        ]
      }
    ]
  },
  {
    "section": "ALTO",
    "service_category": "Risques",
    "qtype": "S",
    "qindex": 26,
    "label": "Votre entreprise sait-elle comment réagir en cas  de fuites ou de destructions de données personnelles (data breach) ?",
    "answers": [
      {
        "aindex": 1,
        "uniqueAnswer": true,
        "atype": "P",
        "label": "Oui",
        "questions_map": [
          {
            "label": "Comment réagissez-vous en cas de fuites ou de destructions de données personnelles ?",
            "branch": 0,
            "level": 26,
            "order": 1
          }
        ]
      },
      {
        "aindex": 2,
        "uniqueAnswer": true,
        "atype": "P",
        "label": "Non",
        "questions_map": [
          {
            "label": "Certaines données traitées sont-elles transférées vers un pays tiers  (hors de l'Union européenne)?",
            "branch": 0,
            "level": 26,
            "order": 1
          }
        ]
      }
    ]
  },
  {
    "section": "ALTO",
    "service_category": "Risques",
    "qtype": "M",
    "qindex": 27,
    "label": "Comment réagissez-vous en cas de fuites ou de destructions de données personnelles ?",
    "answers": [
      {
        "aindex": 1,
        "uniqueAnswer": false,
        "atype": "P",
        "label": "Analyse d'impact des personnes concernées",
        "questions_map": [
          {
            "label": "Certaines données traitées sont-elles transférées vers un pays tiers  (hors de l'Union européenne)?",
            "branch": 0,
            "level": 27,
            "order": 1
          }
        ]
      },
      {
        "aindex": 2,
        "uniqueAnswer": false,
        "atype": "P",
        "label": "Information des personnes concernées en cas de risque élevé pour les droits et libertés de ces dernières",
        "questions_map": [
          {
            "label": "Certaines données traitées sont-elles transférées vers un pays tiers  (hors de l'Union européenne)?",
            "branch": 0,
            "level": 27,
            "order": 1
          }
        ]
      },
      {
        "aindex": 3,
        "uniqueAnswer": false,
        "atype": "P",
        "label": "Tableau des risques (évaluant les niveaux de gravité)",
        "questions_map": [
          {
            "label": "Certaines données traitées sont-elles transférées vers un pays tiers  (hors de l'Union européenne)?",
            "branch": 0,
            "level": 27,
            "order": 1
          }
        ]
      },
      {
        "aindex": 4,
        "uniqueAnswer": false,
        "atype": "P",
        "label": "Mise à exécution d'une procédure de réaction prévue à cet effet",
        "questions_map": [
          {
            "label": "Certaines données traitées sont-elles transférées vers un pays tiers  (hors de l'Union européenne)?",
            "branch": 0,
            "level": 27,
            "order": 1
          }
        ]
      },
      {
        "aindex": 5,
        "uniqueAnswer": false,
        "atype": "P",
        "label": "Formulaire de notification des violations de données de la CNPD",
        "questions_map": [
          {
            "label": "Certaines données traitées sont-elles transférées vers un pays tiers  (hors de l'Union européenne)?",
            "branch": 0,
            "level": 27,
            "order": 1
          }
        ]
      },
      {
        "aindex": 6,
        "uniqueAnswer": false,
        "atype": "P",
        "label": "Prise de mesures pour empêcher que la violation ne se reproduise",
        "questions_map": [
          {
            "label": "Certaines données traitées sont-elles transférées vers un pays tiers  (hors de l'Union européenne)?",
            "branch": 0,
            "level": 27,
            "order": 1
          }
        ]
      },
      {
        "aindex": 7,
        "uniqueAnswer": false,
        "atype": "P",
        "label": "Autre",
        "questions_map": [
          {
            "label": "Certaines données traitées sont-elles transférées vers un pays tiers  (hors de l'Union européenne)?",
            "branch": 0,
            "level": 27,
            "order": 1
          }
        ]
      },
      {
        "aindex": 8,
        "uniqueAnswer": true,
        "atype": "P",
        "label": "Je ne sais pas",
        "questions_map": [
          {
            "label": "Certaines données traitées sont-elles transférées vers un pays tiers  (hors de l'Union européenne)?",
            "branch": 0,
            "level": 27,
            "order": 1
          }
        ]
      }
    ]
  },
  {
    "section": "ALTO",
    "service_category": "Transferts",
    "qtype": "S",
    "qindex": 28,
    "label": "Certaines données traitées sont-elles transférées vers un pays tiers  (hors de l'Union européenne)?",
    "answers": [
      {
        "aindex": 1,
        "uniqueAnswer": true,
        "atype": "P",
        "label": "Oui",
        "questions_map": [
          {
            "label": "Votre entreprise utilise-t-elle des services en ligne gratuits ou payants ?",
            "branch": 0,
            "level": 28,
            "order": 1
          }
        ]
      },
      {
        "aindex": 2,
        "uniqueAnswer": true,
        "atype": "P",
        "label": "Non",
        "questions_map": [
          {
            "label": "Votre entreprise utilise-t-elle des services en ligne gratuits ou payants ?",
            "branch": 0,
            "level": 28,
            "order": 1
          }
        ]
      },
      {
        "aindex": 3,
        "uniqueAnswer": true,
        "atype": "P",
        "label": "En cours de projet",
        "questions_map": [
          {
            "label": "Votre entreprise utilise-t-elle des services en ligne gratuits ou payants ?",
            "branch": 0,
            "level": 28,
            "order": 1
          }
        ]
      },
      {
        "aindex": 4,
        "uniqueAnswer": true,
        "atype": "P",
        "label": "Je ne sais pas",
        "questions_map": [
          {
            "label": "Votre entreprise utilise-t-elle des services en ligne gratuits ou payants ?",
            "branch": 0,
            "level": 28,
            "order": 1
          }
        ]
      }
    ]
  },
  {
    "section": "ALTO",
    "service_category": "Transferts",
    "qtype": "S",
    "qindex": 29,
    "label": "Votre entreprise utilise-t-elle des services en ligne gratuits ou payants ?",
    "answers": [
      {
        "aindex": 1,
        "uniqueAnswer": true,
        "atype": "P",
        "label": "Oui",
        "questions_map": [
          {
            "label": "Votre entreprise vérifie-t-elle où sont localisées les données hébergées par ces fournisseurs de services en ligne ?",
            "branch": 0,
            "level": 29,
            "order": 1
          }
        ]
      },
      {
        "aindex": 2,
        "uniqueAnswer": true,
        "atype": "P",
        "label": "Non",
        "questions_map": [
          {
            "label": "Y a-t-il d'autres aspects non abordés dans le présent questionnaire qui semblent importants de traiter pour votre entreprise ?",
            "branch": 0,
            "level": 29,
            "order": 1
          }
        ]
      },
      {
        "aindex": 3,
        "uniqueAnswer": true,
        "atype": "P",
        "label": "En cours de projet",
        "questions_map": [
          {
            "label": "Votre entreprise vérifie-t-elle où sont localisées les données hébergées par ces fournisseurs de services en ligne ?",
            "branch": 0,
            "level": 29,
            "order": 1
          }
        ]
      },
      {
        "aindex": 4,
        "uniqueAnswer": true,
        "atype": "P",
        "label": "Je ne sais pas",
        "questions_map": [
          {
            "label": "Y a-t-il d'autres aspects non abordés dans le présent questionnaire qui semblent importants de traiter pour votre entreprise ?",
            "branch": 0,
            "level": 29,
            "order": 1
          }
        ]
      }
    ]
  },
  {
    "section": "ALTO",
    "service_category": "Transferts",
    "qtype": "S",
    "qindex": 30,
    "label": "Votre entreprise vérifie-t-elle où sont localisées les données hébergées par ces fournisseurs de services en ligne ?",
    "answers": [
      {
        "aindex": 1,
        "uniqueAnswer": true,
        "atype": "P",
        "label": "Oui",
        "questions_map": [
          {
            "label": "Votre entreprise a-t-elle fait signer un document écrit reprenant les exigences en matière de protection des données à respecter par la société située dans un pays hors de l'Union européenne ?",
            "branch": 0,
            "level": 30,
            "order": 1
          }
        ]
      },
      {
        "aindex": 2,
        "uniqueAnswer": true,
        "atype": "P",
        "label": "Non",
        "questions_map": [
          {
            "label": "Votre entreprise a-t-elle fait signer un document écrit reprenant les exigences en matière de protection des données à respecter par la société située dans un pays hors de l'Union européenne ?",
            "branch": 0,
            "level": 30,
            "order": 1
          }
        ]
      },
      {
        "aindex": 3,
        "uniqueAnswer": true,
        "atype": "P",
        "label": "En cours de projet",
        "questions_map": [
          {
            "label": "Votre entreprise a-t-elle fait signer un document écrit reprenant les exigences en matière de protection des données à respecter par la société située dans un pays hors de l'Union européenne ?",
            "branch": 0,
            "level": 30,
            "order": 1
          }
        ]
      },
      {
        "aindex": 4,
        "uniqueAnswer": true,
        "atype": "P",
        "label": "Je ne sais pas",
        "questions_map": [
          {
            "label": "Votre entreprise a-t-elle fait signer un document écrit reprenant les exigences en matière de protection des données à respecter par la société située dans un pays hors de l'Union européenne ?",
            "branch": 0,
            "level": 30,
            "order": 1
          }
        ]
      }
    ]
  },
  {
    "section": "ALTO",
    "service_category": "Transferts",
    "qtype": "S",
    "qindex": 31,
    "label": "Votre entreprise a-t-elle fait signer un document écrit reprenant les exigences en matière de protection des données à respecter par la société située dans un pays hors de l'Union européenne ?",
    "answers": [
      {
        "aindex": 1,
        "uniqueAnswer": true,
        "atype": "P",
        "label": "Oui",
        "questions_map": [
          {
            "label": "Y a-t-il d'autres aspects non abordés dans le présent questionnaire qui semblent importants de traiter pour votre entreprise ?",
            "branch": 0,
            "level": 31,
            "order": 1
          }
        ]
      },
      {
        "aindex": 2,
        "uniqueAnswer": true,
        "atype": "P",
        "label": "Non",
        "questions_map": [
          {
            "label": "Y a-t-il d'autres aspects non abordés dans le présent questionnaire qui semblent importants de traiter pour votre entreprise ?",
            "branch": 0,
            "level": 31,
            "order": 1
          }
        ]
      },
      {
        "aindex": 3,
        "uniqueAnswer": true,
        "atype": "P",
        "label": "En cours de projet",
        "questions_map": [
          {
            "label": "Y a-t-il d'autres aspects non abordés dans le présent questionnaire qui semblent importants de traiter pour votre entreprise ?",
            "branch": 0,
            "level": 31,
            "order": 1
          }
        ]
      },
      {
        "aindex": 4,
        "uniqueAnswer": true,
        "atype": "P",
        "label": "Je ne sais pas",
        "questions_map": [
          {
            "label": "Y a-t-il d'autres aspects non abordés dans le présent questionnaire qui semblent importants de traiter pour votre entreprise ?",
            "branch": 0,
            "level": 31,
            "order": 1
          }
        ]
      },
      {
        "aindex": 5,
        "uniqueAnswer": false,
        "atype": "P",
        "label": "Non, le fournisseur est établi àdans un Etat fournissant une protection des données adéquate au RGPD<sup>1</sup><p><small>[1] Andorre, Argentine, Canada, Corée du Sud, Îles Féroé, Guernesey, Israël, l'Île de Man, Japon, Jersey, Nouvelle-Zélande, Royaume-Uni, Suisse ou Uruguay.</small></p>",
        "questions_map": [
          {
            "label": "Y a-t-il d'autres aspects non abordés dans le présent questionnaire qui semblent importants de traiter pour votre entreprise ?",
            "branch": 0,
            "level": 31,
            "order": 1
          }
        ]
      }
    ]
  },
  {
    "section": "ALTO",
    "service_category": "Observations",
    "qtype": "T",
    "qindex": 32,
    "label": "Y a-t-il d'autres aspects non abordés dans le présent questionnaire qui semblent importants de traiter pour votre entreprise ?",
    "answers": [
      {
        "aindex": 1,
        "uniqueAnswer": false,
        "atype": "T",
        "label": "Veuillez préciser :"
      }
    ]
  }
]