[
    {
        "section": "Seminar 18th April 2024 Liège",
        "service_category": "General Satisfaction with the event",
        "qtype": "T",
        "qindex": 1,
        "label": "Name of your entity:",
        "answers": [
            {
                "aindex": 1,
                "uniqueAnswer": true,
                "atype": "T",
                "label": "Provide us with more details, please",
                "questions_map": [
                    {
                        "label": "How satisfied were you with the general organization of the event?",
                        "branch": 0,
                        "level": 1,
                        "order": 1
                    }
                ]
            }
        ]
    },
    {
        "section": "Seminar 18th April 2024 Liège",
        "service_category": "General Satisfaction with the event",
        "qtype": "S",
        "qindex": 2,
        "label": "How satisfied were you with the general organization of the event?",
        "answers": [
            {
                "aindex": 1,
                "uniqueAnswer": true,
                "atype": "P",
                "label": "Very satisfied",
                "questions_map": [
                    {
                        "label": "How satisfied were you with the content of the morning conference?",
                        "branch": 0,
                        "level": 2,
                        "order": 1
                    }
                ]
            },
            {
                "aindex": 2,
                "uniqueAnswer": true,
                "atype": "P",
                "label": "Satisfied",
                "questions_map": [
                    {
                        "label": "How satisfied were you with the content of the morning conference?",
                        "branch": 0,
                        "level": 2,
                        "order": 1
                    }
                ]
            },
            {
                "aindex": 3,
                "uniqueAnswer": true,
                "atype": "P",
                "label": "Not satisfied",
                "questions_map": [
                    {
                        "label": "How satisfied were you with the content of the morning conference?",
                        "branch": 0,
                        "level": 2,
                        "order": 1
                    }
                ]
            },
            {
                "aindex": 4,
                "uniqueAnswer": true,
                "atype": "P",
                "label": "N.A",
                "questions_map": [
                    {
                        "label": "How satisfied were you with the content of the morning conference?",
                        "branch": 0,
                        "level": 2,
                        "order": 1
                    }
                ]
            }
        ]
    },
    {
        "section": "Seminar 18th April 2024 Liège",
        "service_category": "General Satisfaction with the event",
        "qtype": "S",
        "qindex": 3,
        "label": "How satisfied were you with the content of the morning conference?",
        "answers": [
            {
                "aindex": 1,
                "uniqueAnswer": true,
                "atype": "P",
                "label": "Very satisfied",
                "questions_map": [
                    {
                        "label": "What are your key takeaways?",
                        "branch": 0,
                        "level": 3,
                        "order": 1
                    }
                ]
            },
            {
                "aindex": 2,
                "uniqueAnswer": true,
                "atype": "P",
                "label": "Satisfied",
                "questions_map": [
                    {
                        "label": "What are your key takeaways?",
                        "branch": 0,
                        "level": 3,
                        "order": 1
                    }
                ]
            },
            {
                "aindex": 3,
                "uniqueAnswer": true,
                "atype": "P",
                "label": "Not satisfied",
                "questions_map": [
                    {
                        "label": "What are your key takeaways?",
                        "branch": 0,
                        "level": 3,
                        "order": 1
                    }
                ]
            },
            {
                "aindex": 4,
                "uniqueAnswer": true,
                "atype": "P",
                "label": "N.A",
                "questions_map": [
                    {
                        "label": "What are your key takeaways?",
                        "branch": 0,
                        "level": 3,
                        "order": 1
                    }
                ]
            }
        ]
    },
    {
        "section": "Seminar 18th April 2024 Liège",
        "service_category": "General Satisfaction with the event",
        "qtype": "T",
        "qindex": 4,
        "label": "What are your key takeaways?",
        "answers": [
            {
                "aindex": 1,
                "uniqueAnswer": true,
                "atype": "T",
                "label": "Provide us with more details, please",
                "questions_map": [
                    {
                        "label": "In which Workshop did you participate in the afternoon?",
                        "branch": 0,
                        "level": 4,
                        "order": 1
                    }
                ]
            }
        ]
    },
    {
        "section": "Seminar 18th April 2024 Liège",
        "service_category": "General Satisfaction with the event",
        "qtype": "M",
        "qindex": 5,
        "label": "In which Workshop did you participate in the afternoon?",
        "answers": [
            {
                "aindex": 1,
                "uniqueAnswer": false,
                "atype": "P",
                "label": "WORKSHOP 1: Strategic foresight – Earth Observation",
                "questions_map": [
                    {
                        "label": "How satisfied were you with the content of the afternoon workshop?",
                        "branch": 0,
                        "level": 5,
                        "order": 1
                    }
                ]
            },
            {
                "aindex": 2,
                "uniqueAnswer": false,
                "atype": "P",
                "label": "WORKSHOP 2: Secure communications",
                "questions_map": [
                    {
                        "label": "How satisfied were you with the content of the afternoon workshop?",
                        "branch": 0,
                        "level": 5,
                        "order": 1
                    }
                ]
            },
            {
                "aindex": 3,
                "uniqueAnswer": false,
                "atype": "P",
                "label": "WORKSHOP 3: Protection of critical space assets",
                "questions_map": [
                    {
                        "label": "How satisfied were you with the content of the afternoon workshop?",
                        "branch": 0,
                        "level": 5,
                        "order": 1
                    }
                ]
            }
        ]
    },
    {
        "section": "Seminar 18th April 2024 Liège",
        "service_category": "General Satisfaction with the event",
        "qtype": "S",
        "qindex": 6,
        "label": "How satisfied were you with the content of the afternoon workshop?",
        "answers": [
            {
                "aindex": 1,
                "uniqueAnswer": true,
                "atype": "P",
                "label": "Very satisfied",
                "questions_map": [
                    {
                        "label": "Do you have additional comments about workshops ?",
                        "branch": 0,
                        "level": 6,
                        "order": 1
                    }
                ]
            },
            {
                "aindex": 2,
                "uniqueAnswer": true,
                "atype": "P",
                "label": "Satisfied",
                "questions_map": [
                    {
                        "label": "Do you have additional comments about workshops ?",
                        "branch": 0,
                        "level": 6,
                        "order": 1
                    }
                ]
            },
            {
                "aindex": 3,
                "uniqueAnswer": true,
                "atype": "P",
                "label": "Not satisfied",
                "questions_map": [
                    {
                        "label": "Do you have additional comments about workshops ?",
                        "branch": 0,
                        "level": 6,
                        "order": 1
                    }
                ]
            },
            {
                "aindex": 4,
                "uniqueAnswer": true,
                "atype": "P",
                "label": "N.A",
                "questions_map": [
                    {
                        "label": "Do you have additional comments about workshops ?",
                        "branch": 0,
                        "level": 6,
                        "order": 1
                    }
                ]
            }
        ]
    },
    {
        "section": "Seminar 18th April 2024 Liège",
        "service_category": "General Satisfaction with the event",
        "qtype": "T",
        "qindex": 7,
        "label": "Do you have additional comments about workshops ?",
        "answers": [
            {
                "aindex": 1,
                "uniqueAnswer": true,
                "atype": "T",
                "label": "Provide us with more details, please",
                "questions_map": [
                    {
                        "label": "Were the actors you expected to meet there?",
                        "branch": 0,
                        "level": 7,
                        "order": 1
                    }
                ]
            }
        ]
    },
    {
        "section": "Seminar 18th April 2024 Liège",
        "service_category": "Networking",
        "qtype": "T",
        "qindex": 8,
        "label": "Were the actors you expected to meet there?",
        "answers": [
            {
                "aindex": 1,
                "uniqueAnswer": true,
                "atype": "T",
                "label": "Provide us with more details, please",
                "questions_map": [
                    {
                        "label": "Did you make unexpected but fruitful connections?",
                        "branch": 0,
                        "level": 8,
                        "order": 1
                    }
                ]
            }
        ]
    },
    {
        "section": "Seminar 18th April 2024 Liège",
        "service_category": "Networking",
        "qtype": "T",
        "qindex": 9,
        "label": "Did you make unexpected but fruitful connections?",
        "answers": [
            {
                "aindex": 1,
                "uniqueAnswer": true,
                "atype": "T",
                "label": "Provide us with more details, please",
                "questions_map": [
                    {
                        "label": "Could you please list the participants you have established connections during the event?",
                        "branch": 0,
                        "level": 9,
                        "order": 1
                    }
                ]
            }
        ]
    },
    {
        "section": "Seminar 18th April 2024 Liège",
        "service_category": "Networking",
        "qtype": "T",
        "qindex": 10,
        "label": "Could you please list the participants you have established connections during the event?",
        "answers": [
            {
                "aindex": 1,
                "uniqueAnswer": true,
                "atype": "T",
                "label": "Provide us with more details, please",
                "questions_map": [
                    {
                        "label": "Have or will any concrete projects result(ed) from the networking sessions?",
                        "branch": 0,
                        "level": 10,
                        "order": 1
                    }
                ]
            }
        ]
    },
    {
        "section": "Seminar 18th April 2024 Liège",
        "service_category": "Networking",
        "qtype": "T",
        "qindex": 11,
        "label": "Have or will any concrete projects result(ed) from the networking sessions?",
        "answers": [
            {
                "aindex": 1,
                "uniqueAnswer": true,
                "atype": "T",
                "label": "Provide us with more details, please",
                "questions_map": [
                    {
                        "label": "If yes, what are the foreseen next steps?",
                        "branch": 0,
                        "level": 11,
                        "order": 1
                    }
                ]
            }
        ]
    },
    {
        "section": "Seminar 18th April 2024 Liège",
        "service_category": "Networking",
        "qtype": "T",
        "qindex": 12,
        "label": "If yes, what are the foreseen next steps?",
        "answers": [
            {
                "aindex": 1,
                "uniqueAnswer": true,
                "atype": "T",
                "label": "Provide us with more details, please",
                "questions_map": [
                    {
                        "label": "How the sectorial co-organisers of this economic programme (Luxembourg Space Agency, Luxinnovation, Luxembourg House of Cybersecurity) could support these next steps?",
                        "branch": 0,
                        "level": 12,
                        "order": 1
                    }
                ]
            }
        ]
    },
    {
        "section": "Seminar 18th April 2024 Liège",
        "service_category": "Networking",
        "qtype": "T",
        "qindex": 13,
        "label": "How the sectorial co-organisers of this economic programme (Luxembourg Space Agency, Luxinnovation, Luxembourg House of Cybersecurity) could support these next steps?",
        "answers": [
            {
                "aindex": 1,
                "uniqueAnswer": true,
                "atype": "T",
                "label": "Provide us with more details, please",
                "questions_map": [
                    {
                        "label": "What could be improved to enhance these networking opportunities during such mission in the future?",
                        "branch": 0,
                        "level": 13,
                        "order": 1
                    }
                ]
            }
        ]
    },
    {
        "section": "Seminar 18th April 2024 Liège",
        "service_category": "Networking",
        "qtype": "T",
        "qindex": 14,
        "label": "What could be improved to enhance these networking opportunities during such mission in the future?",
        "answers": [
            {
                "aindex": 1,
                "uniqueAnswer": true,
                "atype": "T",
                "label": "Provide us with more details, please",
                "questions_map": [
                    {
                        "label": "Do you have additional comments?",
                        "branch": 0,
                        "level": 14,
                        "order": 1
                    }
                ]
            }
        ]
    },
    {
        "section": "Seminar 18th April 2024 Liège",
        "service_category": "Networking",
        "qtype": "T",
        "qindex": 15,
        "label": "Do you have additional comments?",
        "answers": [
            {
                "aindex": 1,
                "uniqueAnswer": true,
                "atype": "T",
                "label": "Provide us with more details, please",
                "questions_map": [
                    {
                        "label": "",
                        "branch": 0,
                        "level": 15,
                        "order": 1
                    }
                ]
            }
        ]
    }
]