[
  {
    "section": "Awareness",
    "service_category": "Awareness",
    "qtype": "S",
    "qindex": 1,
    "label": "How familiar is your organization with Post-Quantum Cryptography (PQC)?",
    "answers": [
      {
        "aindex": 1,
        "uniqueAnswer": true,
        "atype": "P",
        "label": "Not aware",
        "questions_map": [
          {
            "label": "Are your technical teams aware of the implications of quantum computing on current cryptographic systems?",
             "branch": 0,
            "level": 1,
            "order": 1
          }
        ]
      },
      {
        "aindex": 2,
        "uniqueAnswer": true,
        "atype": "P",
        "label": "Heard of it, but no internal discussions",
        "questions_map": [
          {
            "label": "Are your technical teams aware of the implications of quantum computing on current cryptographic systems?",
             "branch": 0,
            "level": 1,
            "order": 1
          }
        ]
      },
      {
        "aindex": 3,
        "uniqueAnswer": true,
        "atype": "P",
        "label": "Moderate awareness with occasional internal discussions.",
        "questions_map": [
          {
            "label": "Are your technical teams aware of the implications of quantum computing on current cryptographic systems?",
             "branch": 0,
            "level": 1,
            "order": 1
          }
        ]
      },
      {
        "aindex": 4,
        "uniqueAnswer": true,
        "atype": "P",
        "label": "Clear understanding and defined roadmap.",
        "questions_map": [
          {
            "label": "Are your technical teams aware of the implications of quantum computing on current cryptographic systems?",
             "branch": 0,
            "level": 1,
            "order": 1
          }
        ]
      }
    ]
  },
  {
    "section": "Awareness",
    "service_category": "Awareness",
    "qtype": "S",
    "qindex": 2,
    "label": "Are your technical teams aware of the implications of quantum computing on current cryptographic systems?",
    "answers": [
      {
        "aindex": 1,
        "uniqueAnswer": true,
        "atype": "P",
        "label": "Yes",
        "questions_map": [
          {
            "label": "Has PQC or quantum risk been included in your organization's security awareness training or risk management?",
             "branch": 0,
            "level": 1,
            "order": 1
          }
        ]
      },
      {
        "aindex": 2,
        "uniqueAnswer": true,
        "atype": "P",
        "label": "No",
        "questions_map": [
          {
            "label": "Do you know which of your current cryptographic systems (e.g., TLS, VPNs, PKI, blockchain) are vulnerable to quantum attacks?",
             "branch": 0,
            "level": 1,
            "order": 2
          }
        ]
      }
    ]
  },
  {
    "section": "Awareness",
    "service_category": "Awareness",
    "qtype": "S",
    "qindex": 3,
    "label": "Do you know which of your current cryptographic systems (e.g., TLS, VPNs, PKI, blockchain) are vulnerable to quantum attacks?",
    "answers": [
      {
        "aindex": 1,
        "uniqueAnswer": true,
        "atype": "P",
        "label": "Yes",
        "questions_map": [
          {
            "label": "Has PQC or quantum risk been included in your organization's security awareness training or risk management?",
              "branch": 0,
            "level": 3,
            "order": 1
          }
        ]
      },
      {
        "aindex": 2,
        "uniqueAnswer": true,
        "atype": "P",
        "label": "No",
        "questions_map": [
          {
            "label": "Has PQC or quantum risk been included in your organization's security awareness training or risk management?",
              "branch": 0,
            "level": 3,
            "order": 1
          }
        ]
      },
      {
        "aindex": 3,
        "uniqueAnswer": true,
        "atype": "P",
        "label": "We are currently assessing this",
        "questions_map": [
          {
            "label": "Has PQC or quantum risk been included in your organization's security awareness training or risk management?",
              "branch": 0,
            "level": 3,
            "order": 1
          }
        ]
      }
    ]
  },
  {
    "section": "Awareness",
    "service_category": "Awareness",
    "qtype": "S",
    "qindex": 4,
    "label": "Has PQC or quantum risk been included in your organization's security awareness training or risk management?",
    "answers": [
      {
        "aindex": 1,
        "uniqueAnswer": true,
        "atype": "P",
        "label": "Yes",
        "questions_map": [
          {
            "label": "When do you believe quantum computers will pose a real-world threat to currently deployed cryptography?",
              "branch": 0,
            "level": 4,
            "order": 1
          }
        ]
      },
      {
        "aindex": 2,
        "uniqueAnswer": true,
        "atype": "P",
        "label": "No",
        "questions_map": [
          {
            "label": "When do you believe quantum computers will pose a real-world threat to currently deployed cryptography?",
              "branch": 0,
            "level": 4,
            "order": 1
          }
        ]
      },
      {
        "aindex": 3,
        "uniqueAnswer": true,
        "atype": "P",
        "label": "Planned in the next 12 months.",
        "questions_map": [
          {
            "label": "When do you believe quantum computers will pose a real-world threat to currently deployed cryptography?",
              "branch": 0,
            "level": 4,
            "order": 1
          }
        ]
      },
      {
        "aindex": 4,
        "uniqueAnswer": true,
        "atype": "P",
        "label": "Not applicable.",
        "questions_map": [
          {
            "label": "When do you believe quantum computers will pose a real-world threat to currently deployed cryptography?",
              "branch": 0,
            "level": 4,
            "order": 1
          }
        ]
      }
    ]
  },
  {
    "section": "Awareness",
    "service_category": "Awareness",
    "qtype": "S",
    "qindex": 5,
    "label": "When do you believe quantum computers will pose a real-world threat to currently deployed cryptography?",
    "answers": [
      {
        "aindex": 1,
        "uniqueAnswer": true,
        "atype": "P",
        "label": "Within 1 – 2 years",
        "questions_map": [
          {
            "label": "Has your organization developed a strategy or roadmap for transitioning to quantum-resistant cryptographic systems?",
              "branch": 0,
            "level": 5,
            "order": 1
          }
        ]
      },
      {
        "aindex": 2,
        "uniqueAnswer": true,
        "atype": "P",
        "label": "3 – 5 years",
        "questions_map": [
          {
            "label": "Has your organization developed a strategy or roadmap for transitioning to quantum-resistant cryptographic systems?",
              "branch": 0,
            "level": 5,
            "order": 1
          }
        ]
      },
      {
        "aindex": 3,
        "uniqueAnswer": true,
        "atype": "P",
        "label": "6 – 10 years",
        "questions_map": [
          {
            "label": "Has your organization developed a strategy or roadmap for transitioning to quantum-resistant cryptographic systems?",
              "branch": 0,
            "level": 5,
            "order": 1
          }
        ]
      },
      {
        "aindex": 4,
        "uniqueAnswer": true,
        "atype": "P",
        "label": "Over 10 years",
        "questions_map": [
          {
            "label": "Has your organization developed a strategy or roadmap for transitioning to quantum-resistant cryptographic systems?",
              "branch": 0,
            "level": 5,
            "order": 1
          }
        ]
      },
      {
        "aindex": 5,
        "uniqueAnswer": true,
        "atype": "P",
        "label": "Not likely to be a threat",
        "questions_map": [
          {
            "label": "Has your organization developed a strategy or roadmap for transitioning to quantum-resistant cryptographic systems?",
              "branch": 0,
            "level": 5,
            "order": 1
          }
        ]
      },
      {
        "aindex": 6,
        "uniqueAnswer": true,
        "atype": "P",
        "label": "Not sure",
        "questions_map": [
          {
            "label": "Has your organization developed a strategy or roadmap for transitioning to quantum-resistant cryptographic systems?",
              "branch": 0,
            "level": 5,
            "order": 1
          }
        ]
      }
    ]
  },
  {
    "section": "Strategy",
    "service_category": "Strategy",
    "qtype": "S",
    "qindex": 6,
    "label": "Has your organization developed a strategy or roadmap for transitioning to quantum-resistant cryptographic systems?",
    "answers": [
      {
        "aindex": 1,
        "uniqueAnswer": true,
        "atype": "P",
        "label": "Yes",
        "questions_map": [
          {
            "label": "Who is driving this initiative internally?",
              "branch": 0,
            "level": 6,
            "order": 1
          }
        ]
      },
      {
        "aindex": 2,
        "uniqueAnswer": true,
        "atype": "P",
        "label": "In Progress",
        "questions_map": [
          {
            "label": "Do you have your leadership Support?",
              "branch": 0,
            "level": 6,
            "order": 2
          }
        ]
      },
      {
        "aindex": 3,
        "uniqueAnswer": true,
        "atype": "P",
        "label": "Planned but not started.",
        "questions_map": [
          {
            "label": "Do you have your leadership Support?",
              "branch": 0,
            "level": 6,
            "order": 2
          }
        ]
      },
      {
        "aindex": 4,
        "uniqueAnswer": true,
        "atype": "P",
        "label": "No plans yet.",
        "questions_map": [
          {
            "label": "Do you have your leadership Support?",
              "branch": 0,
            "level": 6,
            "order": 2
          }
        ]
      }
    ]
  },
  {
    "section": "Strategy",
    "service_category": "Strategy",
    "qtype": "S",
    "qindex": 7,
    "label": "Who is driving this initiative internally?",
    "answers": [
      {
        "aindex": 1,
        "uniqueAnswer": true,
        "atype": "P",
        "label": "CISO/CIO",
        "questions_map": [
          {
            "label": "Do you have your leadership Support?",
              "branch": 0,
            "level": 7,
            "order": 1
          }
        ]
      },
      {
        "aindex": 2,
        "uniqueAnswer": true,
        "atype": "P",
        "label": "IT Security Team",
        "questions_map": [
          {
            "label": "Do you have your leadership Support?",
              "branch": 0,
            "level": 7,
            "order": 1
          }
        ]
      },
      {
        "aindex": 3,
        "uniqueAnswer": true,
        "atype": "P",
        "label": "Compliance/Governance",
        "questions_map": [
          {
            "label": "Do you have your leadership Support?",
              "branch": 0,
            "level": 7,
            "order": 1
          }
        ]
      },
      {
        "aindex": 4,
        "uniqueAnswer": true,
        "atype": "P",
        "label": "External Advisors",
        "questions_map": [
          {
            "label": "Do you have your leadership Support?",
              "branch": 0,
            "level": 7,
            "order": 1
          }
        ]
      },
      {
        "aindex": 5,
        "uniqueAnswer": true,
        "atype": "P",
        "label": "Not sure",
        "questions_map": [
          {
            "label": "Do you have your leadership Support?",
              "branch": 0,
            "level": 7,
            "order": 1
          }
        ]
      }
    ]
  },
  {
    "section": "Strategy",
    "service_category": "Strategy",
    "qtype": "S",
    "qindex": 8,
    "label": "Do you have your leadership Support?",
    "answers": [
      {
        "aindex": 1,
        "uniqueAnswer": true,
        "atype": "P",
        "label": "Yes",
        "questions_map": [
          {
            "label": "What stage is your organization at in its post-quantum transition?",
              "branch": 0,
            "level": 8,
            "order": 1
          }
        ]
      },
      {
        "aindex": 2,
        "uniqueAnswer": true,
        "atype": "P",
        "label": "No",
        "questions_map": [
          {
            "label": "What stage is your organization at in its post-quantum transition?",
              "branch": 0,
            "level": 8,
            "order": 1
          }
        ]
      }
    ]
  },
  {
    "section": "Strategy",
    "service_category": "Strategy",
    "qtype": "S",
    "qindex": 9,
    "label": "What stage is your organization at in its post-quantum transition?",
    "answers": [
      {
        "aindex": 1,
        "uniqueAnswer": true,
        "atype": "P",
        "label": "No awareness.",
        "questions_map": [
          {
            "label": "How important is PQC in your overall cybersecurity strategy?",
              "branch": 0,
            "level": 9,
            "order": 1
          }
        ]
      },
      {
        "aindex": 2,
        "uniqueAnswer": true,
        "atype": "P",
        "label": "Awareness but no planning.",
        "questions_map": [
          {
            "label": "How important is PQC in your overall cybersecurity strategy?",
              "branch": 0,
            "level": 9,
            "order": 1
          }
        ]
      },
      {
        "aindex": 3,
        "uniqueAnswer": true,
        "atype": "P",
        "label": "Planning underway.",
        "questions_map": [
          {
            "label": "How important is PQC in your overall cybersecurity strategy?",
              "branch": 0,
            "level": 9,
            "order": 1
          }
        ]
      },
      {
        "aindex": 4,
        "uniqueAnswer": true,
        "atype": "P",
        "label": "Pilots or proof-of-concepts (PoCs).",
        "questions_map": [
          {
            "label": "How important is PQC in your overall cybersecurity strategy?",
              "branch": 0,
            "level": 9,
            "order": 1
          }
        ]
      },
      {
        "aindex": 5,
        "uniqueAnswer": true,
        "atype": "P",
        "label": "Implementation in production systems.",
        "questions_map": [
          {
            "label": "How important is PQC in your overall cybersecurity strategy?",
              "branch": 0,
            "level": 9,
            "order": 1
          }
        ]
      }
    ]
  },
  {
    "section": "Strategy",
    "service_category": "Strategy",
    "qtype": "S",
    "qindex": 10,
    "label": "How important is PQC in your overall cybersecurity strategy?",
    "answers": [
      {
        "aindex": 1,
        "uniqueAnswer": true,
        "atype": "P",
        "label": "Top priority",
        "questions_map": [
          {
            "label": "Has your organization conducted a cryptographic inventory to identify algorithms and protocols currently in use?",
              "branch": 0,
            "level": 10,
            "order": 1
          }
        ]
      },
      {
        "aindex": 2,
        "uniqueAnswer": true,
        "atype": "P",
        "label": "Medium priority",
        "questions_map": [
          {
            "label": "Has your organization conducted a cryptographic inventory to identify algorithms and protocols currently in use?",
              "branch": 0,
            "level": 10,
            "order": 1
          }
        ]
      },
      {
        "aindex": 3,
        "uniqueAnswer": true,
        "atype": "P",
        "label": "Low priority",
        "questions_map": [
          {
            "label": "Has your organization conducted a cryptographic inventory to identify algorithms and protocols currently in use?",
              "branch": 0,
            "level": 10,
            "order": 1
          }
        ]
      },
      {
        "aindex": 4,
        "uniqueAnswer": true,
        "atype": "P",
        "label": "Not currently prioritized.",
        "questions_map": [
          {
            "label": "Has your organization conducted a cryptographic inventory to identify algorithms and protocols currently in use?",
              "branch": 0,
            "level": 10,
            "order": 1
          }
        ]
      }
    ]
  },
  {
    "section": "Inventory & Readiness",
    "service_category": "Inventory & Readiness",
    "qtype": "S",
    "qindex": 11,
    "label": "Has your organization conducted a cryptographic inventory to identify algorithms and protocols currently in use?",
    "answers": [
      {
        "aindex": 1,
        "uniqueAnswer": true,
        "atype": "P",
        "label": "Yes, but not updated.",
        "questions_map": [
          {
            "label": "Have you assessed which systems would be most vulnerable to a future quantum threat?",
              "branch": 0,
            "level": 11,
            "order": 1
          }
        ]
      },
      {
        "aindex": 2,
        "uniqueAnswer": true,
        "atype": "P",
        "label": "No",
        "questions_map": [
          {
            "label": "Have you assessed which systems would be most vulnerable to a future quantum threat?",
              "branch": 0,
            "level": 11,
            "order": 1
          }
        ]
      },
      {
        "aindex": 3,
        "uniqueAnswer": true,
        "atype": "P",
        "label": "We plan to do in future.",
        "questions_map": [
          {
            "label": "Have you assessed which systems would be most vulnerable to a future quantum threat?",
              "branch": 0,
            "level": 11,
            "order": 1
          }
        ]
      },
      {
        "aindex": 4,
        "uniqueAnswer": true,
        "atype": "P",
        "label": "Not sure",
        "questions_map": [
          {
            "label": "Have you assessed which systems would be most vulnerable to a future quantum threat?",
              "branch": 0,
            "level": 11,
            "order": 1
          }
        ]
      }
    ]
  },
  {
    "section": "Inventory & Readiness",
    "service_category": "Inventory & Readiness",
    "qtype": "S",
    "qindex": 12,
    "label": "Have you assessed which systems would be most vulnerable to a future quantum threat?",
    "answers": [
      {
        "aindex": 1,
        "uniqueAnswer": true,
        "atype": "P",
        "label": "Yes",
        "questions_map": [
          {
            "label": "Are you currently testing or piloting any PQC algorithms?",
              "branch": 0,
            "level": 12,
            "order": 1
          }
        ]
      },
      {
        "aindex": 2,
        "uniqueAnswer": true,
        "atype": "P",
        "label": "In Progress",
        "questions_map": [
          {
            "label": "Are you currently testing or piloting any PQC algorithms?",
              "branch": 0,
            "level": 12,
            "order": 1
          }
        ]
      },
      {
        "aindex": 3,
        "uniqueAnswer": true,
        "atype": "P",
        "label": "No",
        "questions_map": [
          {
            "label": "Are you currently testing or piloting any PQC algorithms?",
              "branch": 0,
            "level": 12,
            "order": 1
          }
        ]
      }
    ]
  },
  {
    "section": "Inventory & Readiness",
    "service_category": "Inventory & Readiness",
    "qtype": "ST",
    "qindex": 13,
    "label": "Are you currently testing or piloting any PQC algorithms?",
    "answers": [
      {
        "aindex": 1,
        "uniqueAnswer": true,
        "atype": "T",
        "label": "Yes",
        "questions_map": [
          {
            "label": "What tools or methods are you using for crypto discovery and inventory?",
              "branch": 0,
            "level": 13,
            "order": 1
          }
        ]
      },
      {
        "aindex": 2,
        "uniqueAnswer": true,
        "atype": "P",
        "label": "No",
        "questions_map": [
          {
            "label": "What tools or methods are you using for crypto discovery and inventory?",
              "branch": 0,
            "level": 13,
            "order": 1
          }
        ]
      }
    ]
  },
  {
    "section": "Inventory & Readiness",
    "service_category": "Inventory & Readiness",
    "qtype": "S",
    "qindex": 14,
    "label": "What tools or methods are you using for crypto discovery and inventory?",
    "answers": [
      {
        "aindex": 1,
        "uniqueAnswer": true,
        "atype": "P",
        "label": "Manual audits",
        "questions_map": [
          {
            "label": "When do you plan to start migrating to PQC?",
              "branch": 0,
            "level": 14,
            "order": 1
          }
        ]
      },
      {
        "aindex": 2,
        "uniqueAnswer": true,
        "atype": "P",
        "label": "Automated scanning tools",
        "questions_map": [
          {
            "label": "When do you plan to start migrating to PQC?",
              "branch": 0,
            "level": 14,
            "order": 1
          }
        ]
      },
      {
        "aindex": 3,
        "uniqueAnswer": true,
        "atype": "P",
        "label": "Asset management platform integration",
        "questions_map": [
          {
            "label": "When do you plan to start migrating to PQC?",
              "branch": 0,
            "level": 14,
            "order": 1
          }
        ]
      },
      {
        "aindex": 4,
        "uniqueAnswer": true,
        "atype": "P",
        "label": "Not using any tools",
        "questions_map": [
          {
            "label": "When do you plan to start migrating to PQC?",
              "branch": 0,
            "level": 14,
            "order": 1
          }
        ]
      },
      {
        "aindex": 5,
        "uniqueAnswer": true,
        "atype": "P",
        "label": "Not applicable / don't know.",
        "questions_map": [
          {
            "label": "When do you plan to start migrating to PQC?",
              "branch": 0,
            "level": 14,
            "order": 1
          }
        ]
      }
    ]
  },
  {
    "section": "Inventory & Readiness",
    "service_category": "Inventory & Readiness",
    "qtype": "S",
    "qindex": 15,
    "label": "When do you plan to start migrating to PQC?",
    "answers": [
      {
        "aindex": 1,
        "uniqueAnswer": true,
        "atype": "P",
        "label": "Currently migrating",
        "questions_map": [
          {
            "label": "Are you prepared to meet impending regulatory requirements around quantum threat resilience?",
              "branch": 0,
            "level": 15,
            "order": 1
          }
        ]
      },
      {
        "aindex": 2,
        "uniqueAnswer": true,
        "atype": "P",
        "label": "1 - 3 years",
        "questions_map": [
          {
            "label": "Are you prepared to meet impending regulatory requirements around quantum threat resilience?",
              "branch": 0,
            "level": 15,
            "order": 1
          }
        ]
      },
      {
        "aindex": 3,
        "uniqueAnswer": true,
        "atype": "P",
        "label": "3 - 5 years",
        "questions_map": [
          {
            "label": "Are you prepared to meet impending regulatory requirements around quantum threat resilience?",
              "branch": 0,
            "level": 15,
            "order": 1
          }
        ]
      },
      {
        "aindex": 4,
        "uniqueAnswer": true,
        "atype": "P",
        "label": "5 - 10 years",
        "questions_map": [
          {
            "label": "Are you prepared to meet impending regulatory requirements around quantum threat resilience?",
              "branch": 0,
            "level": 15,
            "order": 1
          }
        ]
      },
      {
        "aindex": 5,
        "uniqueAnswer": true,
        "atype": "P",
        "label": "Unsure, likely after 10 years, or not at all",
        "questions_map": [
          {
            "label": "Are you prepared to meet impending regulatory requirements around quantum threat resilience?",
              "branch": 0,
            "level": 15,
            "order": 1
          }
        ]
      }
    ]
  },
  {
    "section": "Regulations/Complaince",
    "service_category": "Regulations/Complaince",
    "qtype": "S",
    "qindex": 16,
    "label": "Are you prepared to meet impending regulatory requirements around quantum threat resilience?",
    "answers": [
      {
        "aindex": 1,
        "uniqueAnswer": true,
        "atype": "P",
        "label": "Yes",
        "questions_map": [
          {
            "label": "Are you aware of emerging compliance requirements or government guidelines on PQC?",
              "branch": 0,
            "level": 16,
            "order": 1
          }
        ]
      },
      {
        "aindex": 2,
        "uniqueAnswer": true,
        "atype": "P",
        "label": "No",
        "questions_map": [
          {
            "label": "Are you aware of emerging compliance requirements or government guidelines on PQC?",
              "branch": 0,
            "level": 16,
            "order": 1
          }
        ]
      },
      {
        "aindex": 3,
        "uniqueAnswer": true,
        "atype": "P",
        "label": "Not planned",
        "questions_map": [
          {
            "label": "Are you aware of emerging compliance requirements or government guidelines on PQC?",
              "branch": 0,
            "level": 16,
            "order": 1
          }
        ]
      }
    ]
  },
  {
    "section": "Regulations/Complaince",
    "service_category": "Regulations/Complaince",
    "qtype": "S",
    "qindex": 17,
    "label": "Are you aware of emerging compliance requirements or government guidelines on PQC?",
    "answers": [
      {
        "aindex": 1,
        "uniqueAnswer": true,
        "atype": "P",
        "label": "Yes",
        "questions_map": [
          {
            "label": "Have you engaged with third-party vendors or service providers about their plans for PQC?",
              "branch": 0,
            "level": 17,
            "order": 1
          }
        ]
      },
      {
        "aindex": 2,
        "uniqueAnswer": true,
        "atype": "P",
        "label": "No",
        "questions_map": [
          {
            "label": "Have you engaged with third-party vendors or service providers about their plans for PQC?",
              "branch": 0,
            "level": 17,
            "order": 1
          }
        ]
      },
      {
        "aindex": 3,
        "uniqueAnswer": true,
        "atype": "P",
        "label": "Not sure",
        "questions_map": [
          {
            "label": "Have you engaged with third-party vendors or service providers about their plans for PQC?",
              "branch": 0,
            "level": 17,
            "order": 1
          }
        ]
      }
    ]
  },
  {
    "section": "Vendor & Supply chain",
    "service_category": "Vendor & Supply chain",
    "qtype": "S",
    "qindex": 18,
    "label": "Have you engaged with third-party vendors or service providers about their plans for PQC?",
    "answers": [
      {
        "aindex": 1,
        "uniqueAnswer": true,
        "atype": "P",
        "label": "Yes",
        "questions_map": [
          {
            "label": "Have you assessed your third-party relationships, their cryptologic standards and any potential impacts on post-quantum cryptography?",
              "branch": 0,
            "level": 18,
            "order": 1
          }
        ]
      },
      {
        "aindex": 2,
        "uniqueAnswer": true,
        "atype": "P",
        "label": "No",
        "questions_map": [
          {
            "label": "Have you assessed your third-party relationships, their cryptologic standards and any potential impacts on post-quantum cryptography?",
              "branch": 0,
            "level": 18,
            "order": 1
          }
        ]
      },
      {
        "aindex": 3,
        "uniqueAnswer": true,
        "atype": "P",
        "label": "Not sure",
        "questions_map": [
          {
            "label": "Have you assessed your third-party relationships, their cryptologic standards and any potential impacts on post-quantum cryptography?",
              "branch": 0,
            "level": 18,
            "order": 1
          }
        ]
      }
    ]
  },
  {
    "section": "Vendor & Supply chain",
    "service_category": "Vendor & Supply chain",
    "qtype": "S",
    "qindex": 19,
    "label": "Have you assessed your third-party relationships, their cryptologic standards and any potential impacts on post-quantum cryptography?",
    "answers": [
      {
        "aindex": 1,
        "uniqueAnswer": true,
        "atype": "P",
        "label": "Yes",
        "questions_map": [
          {
            "label": "Have you revised your procurement requirements to address PQC standards and documenting encryption for new solutions?",
              "branch": 0,
            "level": 19,
            "order": 1
          }
        ]
      },
      {
        "aindex": 2,
        "uniqueAnswer": true,
        "atype": "P",
        "label": "No",
        "questions_map": [
          {
            "label": "Have you revised your procurement requirements to address PQC standards and documenting encryption for new solutions?",
              "branch": 0,
            "level": 19,
            "order": 1
          }
        ]
      },
      {
        "aindex": 3,
        "uniqueAnswer": true,
        "atype": "P",
        "label": "Planning in future.",
        "questions_map": [
          {
            "label": "Have you revised your procurement requirements to address PQC standards and documenting encryption for new solutions?",
              "branch": 0,
            "level": 19,
            "order": 1
          }
        ]
      }
    ]
  },
  {
    "section": "Vendor & Supply chain",
    "service_category": "Vendor & Supply chain",
    "qtype": "S",
    "qindex": 20,
    "label": "Have you revised your procurement requirements to address PQC standards and documenting encryption for new solutions?",
    "answers": [
      {
        "aindex": 1,
        "uniqueAnswer": true,
        "atype": "P",
        "label": "Yes",
        "questions_map": [
          {
            "label": "What are the biggest challenges in transitioning to PQC? (Select all that apply)",
              "branch": 0,
            "level": 20,
            "order": 1
          }
        ]
      },
      {
        "aindex": 2,
        "uniqueAnswer": true,
        "atype": "P",
        "label": "No",
        "questions_map": [
          {
            "label": "What are the biggest challenges in transitioning to PQC? (Select all that apply)",
              "branch": 0,
            "level": 20,
            "order": 1
          }
        ]
      },
      {
        "aindex": 3,
        "uniqueAnswer": true,
        "atype": "P",
        "label": "We don’t see the need.",
        "questions_map": [
          {
            "label": "What are the biggest challenges in transitioning to PQC? (Select all that apply)",
              "branch": 0,
            "level": 20,
            "order": 1
          }
        ]
      }
    ]
  },
  {
    "section": "Challenges",
    "service_category": "Challenges",
    "qtype": "MT",
    "qindex": 21,
    "label": "What are the biggest challenges in transitioning to PQC? (Select all that apply)",
    "answers": [
      {
        "aindex": 1,
        "uniqueAnswer": false,
        "atype": "P",
        "label": "Lack of awareness.",
        "questions_map": [
          {
            "label": "Do you have a dedicated PQC leadership role or is it an additional role with current responsibilities?",
              "branch": 0,
            "level": 21,
            "order": 1
          }
        ]
      },
      {
        "aindex": 2,
        "uniqueAnswer": false,
        "atype": "P",
        "label": "Cost",
        "questions_map": [
          {
            "label": "Do you have a dedicated PQC leadership role or is it an additional role with current responsibilities?",
              "branch": 0,
            "level": 21,
            "order": 1
          }
        ]
      },
      {
        "aindex": 3,
        "uniqueAnswer": false,
        "atype": "P",
        "label": "Technical complexity.",
        "questions_map": [
          {
            "label": "Do you have a dedicated PQC leadership role or is it an additional role with current responsibilities?",
              "branch": 0,
            "level": 21,
            "order": 1
          }
        ]
      },
      {
        "aindex": 4,
        "uniqueAnswer": false,
        "atype": "P",
        "label": "Lack of skilled personnel",
        "questions_map": [
          {
            "label": "Do you have a dedicated PQC leadership role or is it an additional role with current responsibilities?",
              "branch": 0,
            "level": 21,
            "order": 1
          }
        ]
      },
      {
        "aindex": 5,
        "uniqueAnswer": false,
        "atype": "P",
        "label": "Waiting for standards to finalize.",
        "questions_map": [
          {
            "label": "Do you have a dedicated PQC leadership role or is it an additional role with current responsibilities?",
              "branch": 0,
            "level": 21,
            "order": 1
          }
        ]
      },
      {
        "aindex": 6,
        "uniqueAnswer": false,
        "atype": "P",
        "label": "No perceived urgency",
        "questions_map": [
          {
            "label": "Do you have a dedicated PQC leadership role or is it an additional role with current responsibilities?",
              "branch": 0,
            "level": 21,
            "order": 1
          }
        ]
      },
      {
        "aindex": 7,
        "uniqueAnswer": false,
        "atype": "P",
        "label": "Legacy systems",
        "questions_map": [
          {
            "label": "Do you have a dedicated PQC leadership role or is it an additional role with current responsibilities?",
              "branch": 0,
            "level": 21,
            "order": 1
          }
        ]
      }
    ]
  },
  {
    "section": "Challenges",
    "service_category": "Challenges",
    "qtype": "S",
    "qindex": 22,
    "label": "Do you have a dedicated PQC leadership role or is it an additional role with current responsibilities?",
    "answers": [
      {
        "aindex": 1,
        "uniqueAnswer": true,
        "atype": "P",
        "label": "Dedicated PQC Role in leadership",
        "questions_map": [
          {
            "label": "Do you have internal staff with sufficient technical knowledge to evaluate and implement PQC solutions?",
              "branch": 0,
            "level": 22,
            "order": 1
          }
        ]
      },
      {
        "aindex": 2,
        "uniqueAnswer": true,
        "atype": "P",
        "label": "Shared responsibility",
        "questions_map": [
          {
            "label": "Do you have internal staff with sufficient technical knowledge to evaluate and implement PQC solutions?",
              "branch": 0,
            "level": 22,
            "order": 1
          }
        ]
      },
      {
        "aindex": 3,
        "uniqueAnswer": true,
        "atype": "P",
        "label": "No clear ownership",
        "questions_map": [
          {
            "label": "Do you have internal staff with sufficient technical knowledge to evaluate and implement PQC solutions?",
              "branch": 0,
            "level": 22,
            "order": 1
          }
        ]
      },
      {
        "aindex": 4,
        "uniqueAnswer": true,
        "atype": "P",
        "label": "Not applicable",
        "questions_map": [
          {
            "label": "Do you have internal staff with sufficient technical knowledge to evaluate and implement PQC solutions?",
              "branch": 0,
            "level": 22,
            "order": 1
          }
        ]
      }
    ]
  },
  {
    "section": "Workforce",
    "service_category": "Workforce",
    "qtype": "S",
    "qindex": 23,
    "label": "Do you have internal staff with sufficient technical knowledge to evaluate and implement PQC solutions?",
    "answers": [
      {
        "aindex": 1,
        "uniqueAnswer": true,
        "atype": "P",
        "label": "Yes – in-house expertise available.",
        "questions_map": [
          {
            "label": "Are there plans to hire or train staff in PQC-related roles in the next 12 months?",
              "branch": 0,
            "level": 23,
            "order": 1
          }
        ]
      },
      {
        "aindex": 2,
        "uniqueAnswer": true,
        "atype": "P",
        "label": "Some knowledge, but would need training or external help.",
        "questions_map": [
          {
            "label": "Are there plans to hire or train staff in PQC-related roles in the next 12 months?",
              "branch": 0,
            "level": 23,
            "order": 1
          }
        ]
      },
      {
        "aindex": 3,
        "uniqueAnswer": true,
        "atype": "P",
        "label": "No – would need external consultants or partners",
        "questions_map": [
          {
            "label": "Are there plans to hire or train staff in PQC-related roles in the next 12 months?",
              "branch": 0,
            "level": 23,
            "order": 1
          }
        ]
      },
      {
        "aindex": 4,
        "uniqueAnswer": true,
        "atype": "P",
        "label": "Not sure",
        "questions_map": [
          {
            "label": "Are there plans to hire or train staff in PQC-related roles in the next 12 months?",
              "branch": 0,
            "level": 23,
            "order": 1
          }
        ]
      }
    ]
  },
  {
    "section": "Workforce",
    "service_category": "Workforce",
    "qtype": "S",
    "qindex": 24,
    "label": "Are there plans to hire or train staff in PQC-related roles in the next 12 months?",
    "answers": [
      {
        "aindex": 1,
        "uniqueAnswer": true,
        "atype": "P",
        "label": "Yes",
        "questions_map": [
          {
            "label": "What challenges do you face in hiring PQC talent?",
              "branch": 0,
            "level": 24,
            "order": 1
          }
        ]
      },
      {
        "aindex": 2,
        "uniqueAnswer": true,
        "atype": "P",
        "label": "No",
        "questions_map": [
          {
            "label": "What challenges do you face in hiring PQC talent?",
              "branch": 0,
            "level": 24,
            "order": 1
          }
        ]
      }
    ]
  },
  {
    "section": "Workforce",
    "service_category": "Workforce",
    "qtype": "M",
    "qindex": 25,
    "label": "What challenges do you face in hiring PQC talent?",
    "answers": [
      {
        "aindex": 1,
        "uniqueAnswer": false,
        "atype": "P",
        "label": "Talent shortage in the market.",
        "questions_map": [
          {
            "label": "Would your organization benefit from external PQC training or workshops?",
              "branch": 0,
            "level": 25,
            "order": 1
          }
        ]
      },
      {
        "aindex": 2,
        "uniqueAnswer": false,
        "atype": "P",
        "label": "Budget constraints.",
        "questions_map": [
          {
            "label": "Would your organization benefit from external PQC training or workshops?",
              "branch": 0,
            "level": 25,
            "order": 1
          }
        ]
      },
      {
        "aindex": 3,
        "uniqueAnswer": false,
        "atype": "P",
        "label": "Inability to compete with tech firms.",
        "questions_map": [
          {
            "label": "Would your organization benefit from external PQC training or workshops?",
              "branch": 0,
            "level": 25,
            "order": 1
          }
        ]
      },
      {
        "aindex": 4,
        "uniqueAnswer": false,
        "atype": "P",
        "label": "Lack of internal PQC strategy.",
        "questions_map": [
          {
            "label": "Would your organization benefit from external PQC training or workshops?",
              "branch": 0,
            "level": 25,
            "order": 1
          }
        ]
      },
      {
        "aindex": 5,
        "uniqueAnswer": false,
        "atype": "P",
        "label": "No challenges.",
        "questions_map": [
          {
            "label": "Would your organization benefit from external PQC training or workshops?",
              "branch": 0,
            "level": 25,
            "order": 1
          }
        ]
      }
    ]
  },
  {
    "section": "Workforce",
    "service_category": "Workforce",
    "qtype": "S",
    "qindex": 26,
    "label": "Would your organization benefit from external PQC training or workshops?",
    "answers": [
      {
        "aindex": 1,
        "uniqueAnswer": true,
        "atype": "P",
        "label": "Yes – urgently needed",
        "questions_map": [
          {
            "label": "How would you rate your workforce's overall PQC readiness?",
              "branch": 0,
            "level": 26,
            "order": 1
          }
        ]
      },
      {
        "aindex": 2,
        "uniqueAnswer": true,
        "atype": "P",
        "label": "Possibly – for technical teams",
        "questions_map": [
          {
            "label": "How would you rate your workforce's overall PQC readiness?",
              "branch": 0,
            "level": 26,
            "order": 1
          }
        ]
      },
      {
        "aindex": 3,
        "uniqueAnswer": true,
        "atype": "P",
        "label": "Not necessary",
        "questions_map": [
          {
            "label": "How would you rate your workforce's overall PQC readiness?",
              "branch": 0,
            "level": 26,
            "order": 1
          }
        ]
      },
      {
        "aindex": 4,
        "uniqueAnswer": true,
        "atype": "P",
        "label": "Not sure",
        "questions_map": [
          {
            "label": "How would you rate your workforce's overall PQC readiness?",
              "branch": 0,
            "level": 26,
            "order": 1
          }
        ]
      }
    ]
  },
  {
    "section": "Workforce",
    "service_category": "Workforce",
    "qtype": "S",
    "qindex": 27,
    "label": "How would you rate your workforce's overall PQC readiness?",
    "answers": [
      {
        "aindex": 1,
        "uniqueAnswer": true,
        "atype": "P",
        "label": "High — well-prepared and growing",
        "questions_map": [
          {
            "label": "How does your organization classify its data in terms of sensitivity and risk?",
              "branch": 0,
            "level": 27,
            "order": 1
          }
        ]
      },
      {
        "aindex": 2,
        "uniqueAnswer": true,
        "atype": "P",
        "label": "Moderate — skills exist but are siloed.",
        "questions_map": [
          {
            "label": "How does your organization classify its data in terms of sensitivity and risk?",
              "branch": 0,
            "level": 27,
            "order": 1
          }
        ]
      },
      {
        "aindex": 3,
        "uniqueAnswer": true,
        "atype": "P",
        "label": "Low — major gaps in skills and planning.",
        "questions_map": [
          {
            "label": "How does your organization classify its data in terms of sensitivity and risk?",
              "branch": 0,
            "level": 27,
            "order": 1
          }
        ]
      },
      {
        "aindex": 4,
        "uniqueAnswer": true,
        "atype": "P",
        "label": "Not assessed",
        "questions_map": [
          {
            "label": "How does your organization classify its data in terms of sensitivity and risk?",
              "branch": 0,
            "level": 27,
            "order": 1
          }
        ]
      }
    ]
  },
  {
    "section": "Inventory & Readiness",
    "service_category": "Inventory & Readiness",
    "qtype": "S",
    "qindex": 28,
    "label": "How does your organization classify its data in terms of sensitivity and risk?",
    "answers": [
      {
        "aindex": 1,
        "uniqueAnswer": true,
        "atype": "P",
        "label": "High-risk data"
      },
      {
        "aindex": 2,
        "uniqueAnswer": true,
        "atype": "P",
        "label": "Medium-risk data"
      },
      {
        "aindex": 3,
        "uniqueAnswer": true,
        "atype": "P",
        "label": "Low-risk data"
      },
      {
        "aindex": 4,
        "uniqueAnswer": true,
        "atype": "P",
        "label": "Not sure or no classification done."
      }
    ]
  }
]
